Entregas finales/códigos/paridad/control.v
module control(

    input clk,
    input rst,
    input init,
    input x,
    input lsb_count,

    output reg ld,
    output reg sum,
    output reg done,
    output reg pari

);

parameter START   = 3'd0;
parameter LOAD    = 3'd1;
parameter SUM_SH  = 3'd2;
parameter CHECK_1 = 3'd3;
parameter CHECK_2 = 3'd4;
parameter PARI    = 3'd5;
parameter DONE    = 3'd6;

reg [2:0] state;


//======================================
// Máquina de estados
//======================================

always @(posedge clk) begin

    if (rst)
        state <= START;

    else begin

        case(state)

            START:
                if(init)
                    state <= LOAD;
                else
                    state <= START;

            LOAD:
                state <= SUM_SH;

            SUM_SH:
                state <= CHECK_1;

            CHECK_1:
                if(x)
                    state <= PARI;
                else
                    state <= SUM_SH;

            PARI:
                state <= DONE;

            DONE:
                state <= START;

            default:
                state <= START;

        endcase

    end

end


//======================================
// Lógica de salida
//======================================

always @(*) begin

    ld   = 0;
    sum  = 0;
    done = 0;
    pari = 0;

    case(state)

        START: begin
            ld   = 0;
            sum  = 0;
            done = 0;
            pari = 0;
        end

        LOAD: begin
            ld   = 1;
            sum  = 0;
            done = 0;
            pari = 0;
        end

        SUM_SH: begin
            ld   = 0;
            sum  = 1;
            done = 0;
            pari = 0;
        end

        CHECK_1: begin
            ld   = 0;
            sum  = 0;
            done = 0;
            pari = 0;
        end

        CHECK_2: begin
            ld   = 0;
            sum  = 0;
            done = 0;
            pari = 0;
        end

        PARI: begin
            ld   = 0;
            sum  = 0;
            done = 0;
            pari = 1;
        end


        DONE: begin
            ld   = 0;
            sum  = 0;
            done = 1;
            pari = 0;
        end

    endcase

end

endmodule

Entregas finales/códigos/paridad/bit_par.v
module bit_par(

    input clk,
    input rst,
    input ld,
    input bit_in,

    output reg bit_out

);

always @(negedge clk) begin

    if(rst)
        bit_out <= 1'b0;

    else if(ld)
        bit_out <= bit_in;

    else
        bit_out <= bit_out;

end

endmodule

Entregas finales/códigos/paridad/i.v
module i (

    input clk,
    input ld,
    input resta,


    output reg [5:0] out_i

);

always @(negedge clk) begin

    if(ld)
        out_i <= 6'd32;

    else if(resta)
        out_i <= out_i - 1;

    else
        out_i <= out_i;

end

endmodule

Entregas finales/códigos/paridad/count.v
module count(

    input clk,
    input ld,
    input rst,
    input sum,
    input bit_A,

    output reg [5:0] out_count

);

always @(negedge clk) begin

    if(ld)
        out_count <= 6'd0;


    else if(sum)
        out_count <= out_count + bit_A;

    else
        out_count <= out_count;

end

endmodule

Entregas finales/códigos/paridad/reg_A.v
module reg_A(
    input clk,
    input rst,
    input ld,
    input sh,
    input [31:0] A_in,

    output reg [31:0] A_out
);

always @(negedge clk) begin

    if(rst)
        A_out <= 0;

    else if(ld)
        A_out <= A_in;

    else if(sh)
        A_out <= A_out >> 1;

end

endmodule

Entregas finales/códigos/paridad/paridad.v
module paridad(

    input clk,
    input rst,
    input init,
    input [31:0] A_in,

    output bit_out,
    output done

);

//======================================
// Señales internas
//======================================

wire [31:0] w_A;
wire [5:0]  w_count;
wire [5:0]  w_i;

wire ld;
wire sum;
wire pari;

wire x;


//======================================
// Señal de fin de iteraciones
//======================================

assign x = (w_i == 6'd0);


//======================================
// Registro A
//======================================

reg_A registro_A(

    .clk(clk),
    .rst(rst),
    .ld(ld),
    .sh(sum),
    .A_in(A_in),
    .A_out(w_A)

);


//======================================
// Contador de unos
//======================================

count contador(

    .clk(clk),
    .ld(ld),
    .sum(sum),
    .bit_A(w_A[0]),
    .out_count(w_count)

);


//======================================
// Contador de iteraciones
//======================================

i contador_i(

    .clk(clk),
    .ld(ld),
    .resta(sum),
    .out_i(w_i)

);


//======================================
// Registro del bit de paridad
//======================================

bit_par registro_paridad(

    .clk(clk),
    .rst(rst),
    .ld(pari),
    .bit_in(w_count[0]),
    .bit_out(bit_out)

);


//======================================
// Máquina de control
//======================================

control controlador(

    .clk(clk),
    .rst(rst),
    .init(init),
    .x(x),                  // <-- CORREGIDO
    .lsb_count(w_count[0]),

    .ld(ld),
    .sum(sum),
    .done(done),
    .pari(pari)

);

endmodule

Entregas finales/códigos/paridad/paridad_TB.v
`timescale 1ns/1ps

module paridad_TB;

    reg clk;
    reg rst;
    reg init;
    reg [31:0] A_in;

    wire bit_out;
    wire done;


    paridad uut(

        .clk(clk),
        .rst(rst),
        .init(init),
        .A_in(A_in),

        .bit_out(bit_out),
        .done(done)

    );



    // Generación del reloj


    always #10 clk = ~clk;



    // Pruebas


    initial begin

        $dumpfile("paridad_TB.vcd");
        $dumpvars(0, paridad_TB);

        clk = 0;
        rst=1;
        init = 0;
        A_in = 0;

        #20;
        rst=0;
        #20;
        // PRUEBA 1

        A_in = 32'd13;

        init = 1;
        #20;
        init = 0;

        @(posedge done);

        #40;


        $display("PRUEBA 1");
        $display("Numero = %d",A_in);
        $display("Bit de paridad = %d",bit_out);

        #100;

        // PRUEBA 2

        A_in = 32'd10;

        init = 1;
        #20;
        init = 0;

        @(posedge done);

        #40;

        $display("PRUEBA 2");
        $display("Numero = %d",A_in);
        $display("Bit de paridad = %d",bit_out);

        #40;

        $finish;

    end

endmodule

Entregas finales/códigos/paridad/paridad_TB.vcd
$date
	Mon Jul 13 20:53:27 2026
$end
$version
	Icarus Verilog
$end
$timescale
	1ps
$end
$scope module paridad_TB $end
$var wire 1 ! done $end
$var wire 1 " bit_out $end
$var reg 32 # A_in [31:0] $end
$var reg 1 $ clk $end
$var reg 1 % init $end
$var reg 1 & rst $end
$scope module uut $end
$var wire 32 ' A_in [31:0] $end
$var wire 1 $ clk $end
$var wire 1 % init $end
$var wire 1 & rst $end
$var wire 1 ( x $end
$var wire 6 ) w_i [5:0] $end
$var wire 6 * w_count [5:0] $end
$var wire 32 + w_A [31:0] $end
$var wire 1 , sum $end
$var wire 1 - pari $end
$var wire 1 . ld $end
$var wire 1 ! done $end
$var wire 1 " bit_out $end
$scope module contador $end
$var wire 1 / bit_A $end
$var wire 1 $ clk $end
$var wire 1 0 rst $end
$var wire 1 , sum $end
$var wire 1 . ld $end
$var reg 6 1 out_count [5:0] $end
$upscope $end
$scope module contador_i $end
$var wire 1 $ clk $end
$var wire 1 , resta $end
$var wire 1 . ld $end
$var reg 6 2 out_i [5:0] $end
$upscope $end
$scope module controlador $end
$var wire 1 $ clk $end
$var wire 1 % init $end
$var wire 1 3 lsb_count $end
$var wire 1 & rst $end
$var wire 1 ( x $end
$var parameter 3 4 CHECK_1 $end
$var parameter 3 5 CHECK_2 $end
$var parameter 3 6 DONE $end
$var parameter 3 7 LOAD $end
$var parameter 3 8 PARI $end
$var parameter 3 9 START $end
$var parameter 3 : SUM_SH $end
$var reg 1 ! done $end
$var reg 1 . ld $end
$var reg 1 - pari $end
$var reg 3 ; state [2:0] $end
$var reg 1 , sum $end
$upscope $end
$scope module registro_A $end
$var wire 32 < A_in [31:0] $end
$var wire 1 $ clk $end
$var wire 1 . ld $end
$var wire 1 & rst $end
$var wire 1 , sh $end
$var reg 32 = A_out [31:0] $end
$upscope $end
$scope module registro_paridad $end
$var wire 1 > bit_in $end
$var wire 1 $ clk $end
$var wire 1 - ld $end
$var wire 1 & rst $end
$var reg 1 " bit_out $end
$upscope $end
$upscope $end
$upscope $end
$enddefinitions $end
$comment Show the parameter values. $end
$dumpall
b10 :
b0 9
b101 8
b1 7
b110 6
b100 5
b11 4
$end
#0
$dumpvars
x>
b0 =
b0 <
bx ;
x3
bx 2
bx 1
z0
0/
x.
x-
x,
b0 +
bx *
bx )
x(
b0 '
1&
0%
0$
b0 #
0"
x!
$end
#10000
0-
0!
0,
0.
b0 ;
1$
#20000
0$
0&
#30000
1$
#40000
0$
1%
b1101 #
b1101 '
b1101 <
#50000
1.
b1 ;
1$
#60000
03
0>
1/
0(
b100000 )
b100000 2
b0 *
b0 1
b1101 +
b1101 =
0$
0%
#70000
1,
0.
b10 ;
1$
#80000
0/
13
1>
b110 +
b110 =
b1 *
b1 1
b11111 )
b11111 2
0$
#90000
0,
b11 ;
1$
#100000
0$
#110000
1,
b10 ;
1$
#120000
1/
b11 +
b11 =
b11110 )
b11110 2
0$
#130000
0,
b11 ;
1$
#140000
0$
#150000
1,
b10 ;
1$
#160000
03
0>
b1 +
b1 =
b10 *
b10 1
b11101 )
b11101 2
0$
#170000
0,
b11 ;
1$
#180000
0$
#190000
1,
b10 ;
1$
#200000
0/
13
1>
b0 +
b0 =
b11 *
b11 1
b11100 )
b11100 2
0$
#210000
0,
b11 ;
1$
#220000
0$
#230000
1,
b10 ;
1$
#240000
b11011 )
b11011 2
0$
#250000
0,
b11 ;
1$
#260000
0$
#270000
1,
b10 ;
1$
#280000
b11010 )
b11010 2
0$
#290000
0,
b11 ;
1$
#300000
0$
#310000
1,
b10 ;
1$
#320000
b11001 )
b11001 2
0$
#330000
0,
b11 ;
1$
#340000
0$
#350000
1,
b10 ;
1$
#360000
b11000 )
b11000 2
0$
#370000
0,
b11 ;
1$
#380000
0$
#390000
1,
b10 ;
1$
#400000
b10111 )
b10111 2
0$
#410000
0,
b11 ;
1$
#420000
0$
#430000
1,
b10 ;
1$
#440000
b10110 )
b10110 2
0$
#450000
0,
b11 ;
1$
#460000
0$
#470000
1,
b10 ;
1$
#480000
b10101 )
b10101 2
0$
#490000
0,
b11 ;
1$
#500000
0$
#510000
1,
b10 ;
1$
#520000
b10100 )
b10100 2
0$
#530000
0,
b11 ;
1$
#540000
0$
#550000
1,
b10 ;
1$
#560000
b10011 )
b10011 2
0$
#570000
0,
b11 ;
1$
#580000
0$
#590000
1,
b10 ;
1$
#600000
b10010 )
b10010 2
0$
#610000
0,
b11 ;
1$
#620000
0$
#630000
1,
b10 ;
1$
#640000
b10001 )
b10001 2
0$
#650000
0,
b11 ;
1$
#660000
0$
#670000
1,
b10 ;
1$
#680000
b10000 )
b10000 2
0$
#690000
0,
b11 ;
1$
#700000
0$
#710000
1,
b10 ;
1$
#720000
b1111 )
b1111 2
0$
#730000
0,
b11 ;
1$
#740000
0$
#750000
1,
b10 ;
1$
#760000
b1110 )
b1110 2
0$
#770000
0,
b11 ;
1$
#780000
0$
#790000
1,
b10 ;
1$
#800000
b1101 )
b1101 2
0$
#810000
0,
b11 ;
1$
#820000
0$
#830000
1,
b10 ;
1$
#840000
b1100 )
b1100 2
0$
#850000
0,
b11 ;
1$
#860000
0$
#870000
1,
b10 ;
1$
#880000
b1011 )
b1011 2
0$
#890000
0,
b11 ;
1$
#900000
0$
#910000
1,
b10 ;
1$
#920000
b1010 )
b1010 2
0$
#930000
0,
b11 ;
1$
#940000
0$
#950000
1,
b10 ;
1$
#960000
b1001 )
b1001 2
0$
#970000
0,
b11 ;
1$
#980000
0$
#990000
1,
b10 ;
1$
#1000000
b1000 )
b1000 2
0$
#1010000
0,
b11 ;
1$
#1020000
0$
#1030000
1,
b10 ;
1$
#1040000
b111 )
b111 2
0$
#1050000
0,
b11 ;
1$
#1060000
0$
#1070000
1,
b10 ;
1$
#1080000
b110 )
b110 2
0$
#1090000
0,
b11 ;
1$
#1100000
0$
#1110000
1,
b10 ;
1$
#1120000
b101 )
b101 2
0$
#1130000
0,
b11 ;
1$
#1140000
0$
#1150000
1,
b10 ;
1$
#1160000
b100 )
b100 2
0$
#1170000
0,
b11 ;
1$
#1180000
0$
#1190000
1,
b10 ;
1$
#1200000
b11 )
b11 2
0$
#1210000
0,
b11 ;
1$
#1220000
0$
#1230000
1,
b10 ;
1$
#1240000
b10 )
b10 2
0$
#1250000
0,
b11 ;
1$
#1260000
0$
#1270000
1,
b10 ;
1$
#1280000
b1 )
b1 2
0$
#1290000
0,
b11 ;
1$
#1300000
0$
#1310000
1,
b10 ;
1$
#1320000
1(
b0 )
b0 2
0$
#1330000
0,
b11 ;
1$
#1340000
0$
#1350000
1-
b101 ;
1$
#1360000
1"
0$
#1370000
1!
0-
b110 ;
1$
#1380000
0$
#1390000
0!
b0 ;
1$
#1400000
0$
#1410000
1$
#1420000
0$
#1430000
1$
#1440000
0$
#1450000
1$
#1460000
0$
#1470000
1$
#1480000
0$
#1490000
1$
#1500000
0$
#1510000
1.
b1 ;
1$
1%
b1010 #
b1010 '
b1010 <
#1520000
03
0>
b1010 +
b1010 =
b0 *
b0 1
0(
b100000 )
b100000 2
0$
#1530000
1,
0.
b10 ;
1$
0%
#1540000
1/
b11111 )
b11111 2
b101 +
b101 =
0$
#1550000
0,
b11 ;
1$
#1560000
0$
#1570000
1,
b10 ;
1$
#1580000
13
1>
0/
b11110 )
b11110 2
b1 *
b1 1
b10 +
b10 =
0$
#1590000
0,
b11 ;
1$
#1600000
0$
#1610000
1,
b10 ;
1$
#1620000
1/
b11101 )
b11101 2
b1 +
b1 =
0$
#1630000
0,
b11 ;
1$
#1640000
0$
#1650000
1,
b10 ;
1$
#1660000
03
0>
0/
b11100 )
b11100 2
b10 *
b10 1
b0 +
b0 =
0$
#1670000
0,
b11 ;
1$
#1680000
0$
#1690000
1,
b10 ;
1$
#1700000
b11011 )
b11011 2
0$
#1710000
0,
b11 ;
1$
#1720000
0$
#1730000
1,
b10 ;
1$
#1740000
b11010 )
b11010 2
0$
#1750000
0,
b11 ;
1$
#1760000
0$
#1770000
1,
b10 ;
1$
#1780000
b11001 )
b11001 2
0$
#1790000
0,
b11 ;
1$
#1800000
0$
#1810000
1,
b10 ;
1$
#1820000
b11000 )
b11000 2
0$
#1830000
0,
b11 ;
1$
#1840000
0$
#1850000
1,
b10 ;
1$
#1860000
b10111 )
b10111 2
0$
#1870000
0,
b11 ;
1$
#1880000
0$
#1890000
1,
b10 ;
1$
#1900000
b10110 )
b10110 2
0$
#1910000
0,
b11 ;
1$
#1920000
0$
#1930000
1,
b10 ;
1$
#1940000
b10101 )
b10101 2
0$
#1950000
0,
b11 ;
1$
#1960000
0$
#1970000
1,
b10 ;
1$
#1980000
b10100 )
b10100 2
0$
#1990000
0,
b11 ;
1$
#2000000
0$
#2010000
1,
b10 ;
1$
#2020000
b10011 )
b10011 2
0$
#2030000
0,
b11 ;
1$
#2040000
0$
#2050000
1,
b10 ;
1$
#2060000
b10010 )
b10010 2
0$
#2070000
0,
b11 ;
1$
#2080000
0$
#2090000
1,
b10 ;
1$
#2100000
b10001 )
b10001 2
0$
#2110000
0,
b11 ;
1$
#2120000
0$
#2130000
1,
b10 ;
1$
#2140000
b10000 )
b10000 2
0$
#2150000
0,
b11 ;
1$
#2160000
0$
#2170000
1,
b10 ;
1$
#2180000
b1111 )
b1111 2
0$
#2190000
0,
b11 ;
1$
#2200000
0$
#2210000
1,
b10 ;
1$
#2220000
b1110 )
b1110 2
0$
#2230000
0,
b11 ;
1$
#2240000
0$
#2250000
1,
b10 ;
1$
#2260000
b1101 )
b1101 2
0$
#2270000
0,
b11 ;
1$
#2280000
0$
#2290000
1,
b10 ;
1$
#2300000
b1100 )
b1100 2
0$
#2310000
0,
b11 ;
1$
#2320000
0$
#2330000
1,
b10 ;
1$
#2340000
b1011 )
b1011 2
0$
#2350000
0,
b11 ;
1$
#2360000
0$
#2370000
1,
b10 ;
1$
#2380000
b1010 )
b1010 2
0$
#2390000
0,
b11 ;
1$
#2400000
0$
#2410000
1,
b10 ;
1$
#2420000
b1001 )
b1001 2
0$
#2430000
0,
b11 ;
1$
#2440000
0$
#2450000
1,
b10 ;
1$
#2460000
b1000 )
b1000 2
0$
#2470000
0,
b11 ;
1$
#2480000
0$
#2490000
1,
b10 ;
1$
#2500000
b111 )
b111 2
0$
#2510000
0,
b11 ;
1$
#2520000
0$
#2530000
1,
b10 ;
1$
#2540000
b110 )
b110 2
0$
#2550000
0,
b11 ;
1$
#2560000
0$
#2570000
1,
b10 ;
1$
#2580000
b101 )
b101 2
0$
#2590000
0,
b11 ;
1$
#2600000
0$
#2610000
1,
b10 ;
1$
#2620000
b100 )
b100 2
0$
#2630000
0,
b11 ;
1$
#2640000
0$
#2650000
1,
b10 ;
1$
#2660000
b11 )
b11 2
0$
#2670000
0,
b11 ;
1$
#2680000
0$
#2690000
1,
b10 ;
1$
#2700000
b10 )
b10 2
0$
#2710000
0,
b11 ;
1$
#2720000
0$
#2730000
1,
b10 ;
1$
#2740000
b1 )
b1 2
0$
#2750000
0,
b11 ;
1$
#2760000
0$
#2770000
1,
b10 ;
1$
#2780000
1(
b0 )
b0 2
0$
#2790000
0,
b11 ;
1$
#2800000
0$
#2810000
1-
b101 ;
1$
#2820000
0"
0$
#2830000
1!
0-
b110 ;
1$
#2840000
0$
#2850000
0!
b0 ;
1$
