Entregas finales/códigos/raizcua/count.v
module count (
    input clk,
    input ld,
    input resta,
    input [5:0] n,                 
    output reg [5:0] out_count); 
    always @(negedge clk) begin
        if (ld)
            out_count <= n;                  
        else if (resta)
            out_count <= out_count - 1;      
        else
            out_count <= out_count;          
    end
endmodule

Entregas finales/códigos/raizcua/sum_C2.v
module sum_C2 (
    input  [31:0] resi_in,
    input  [31:0] term_in,   // = (Comp<<1)+1, ya armado afuera
    output [31:0] new_resi,
    output SUF
);

assign new_resi = resi_in - term_in;
assign SUF = ~new_resi[31];   // SUF=1 si el resultado es >=0 

endmodule

Entregas finales/códigos/raizcua/reg_comp.v
module reg_comp(
    input clk,
    input reset,             
    input ld_comp,            
    input  [15:0] r_in,      
    output reg [31:0] comp_out
);

always @(negedge clk) begin
    if (reset)
        comp_out <= 32'b0;
    else if (ld_comp)
        comp_out <= {16'b0, r_in};  
    else
        comp_out <= comp_out;
end

endmodule

Entregas finales/códigos/raizcua/reg_R.v
module reg_R(
    input clk,
    input ld,               
    input sh,               
    input ro,               
    output reg [15:0] R_out  
);

always @(negedge clk) begin
    if (ld)
        R_out <= 16'b0;
    else if (sh)
        R_out <= R_out << 1;
    else if (ro)
        R_out[0] <= 1'b1;
    else
        R_out <= R_out;
end

endmodule

Entregas finales/códigos/raizcua/resi_subA.v
module resi_subA(
    input clk,
    input ld,              
    input sh,               
    input nr,              
    input  [31:0] radicando,
    input  [31:0] new_resi, 
    output [31:0] resi_out, 
    output [31:0] subA_out  
);

reg [63:0] A;

always @(negedge clk) begin
    if (ld)
        A <= {32'b0, radicando};
    else if (sh)
        A <= A << 2;
    else if (nr)
        A <= {new_resi, A[31:0]};
    else
        A <= A;
end

assign resi_out = A[63:32];
assign subA_out = A[31:0];

endmodule

Entregas finales/códigos/raizcua/control.v
module control (
    input clk,
    input rst_hardware,
    input init,
    input suf,     // viene del sum_C2
    input z,       // viene del contador 
    output reg ld,
    output reg sh,
    output reg ro,
    output reg nr,
    output reg ld_comp,
    output reg done
);

// Definicion de los estados
reg [2:0] state, next_state;
localparam START   = 3'b000,
           CORRER   = 3'b001,
           LD_COMP  = 3'b010,
           SUM      = 3'b011,
           R_0      = 3'b100,
           DONE     = 3'b101;

// 1. Bloque secuencial:
always @(posedge clk) begin
    if (rst_hardware) begin
        state <= START;
    end else begin
        case(state)
            START: begin
                if (init)
                    state <= CORRER;
                else
                    state <= START;
            end
            CORRER: begin
                state <= LD_COMP;
            end
            LD_COMP: begin
                if (suf)
                    state <= SUM;
                else
                    state <= R_0;
            end
            SUM: begin
                if (z)
                    state <= DONE;
                else
                    state <= CORRER;
            end
            R_0: begin
                if (z)
                    state <= DONE;
                else
                    state <= CORRER;
            end
            DONE: begin
                if (~init)
                    state <= START;
                else
                    state <= DONE;
            end
            default: state <= START;
        endcase
    end
end

// 2. Bloque combinacional:
always @(*) begin
    case(state)
        START: begin
            done    = 0;
            sh      = 0;
            ld      = 1;
            nr      = 0;
            ro      = 0;
            ld_comp = 0;
        end
        CORRER: begin
            done    = 0;
            sh      = 1;
            ld      = 0;
            nr      = 0;
            ro      = 0;
            ld_comp = 0;
        end
        LD_COMP: begin
            done    = 0;
            sh      = 0;
            ld      = 0;
            nr      = 0;
            ro      = 0;
            ld_comp = 1;
        end
        SUM: begin
            done    = 0;
            sh      = 0;
            ld      = 0;
            nr      = 1;
            ro      = 1;
            ld_comp = 0;
        end
        R_0: begin
            done    = 0;
            sh      = 0;
            ld      = 0;
            nr      = 0;
            ro      = 0;
            ld_comp = 0;
        end
        DONE: begin
            done    = 1;
            sh      = 0;
            ld      = 0;
            nr      = 0;
            ro      = 0;
            ld_comp = 0;
        end
        default: begin
            done    = 0;
            sh      = 0;
            ld      = 0;
            nr      = 0;
            ro      = 0;
            ld_comp = 0;
        end
    endcase
end

endmodule

Entregas finales/códigos/raizcua/raiz.v
module raiz(
    input clk,
    input rst_hardware,
    input init,
    input  [31:0] a,          // radicando
    output [15:0] R,          // resultado (raiz), n/2 bits
    output [31:0] resi,       // residuo final
    output done_raiz
);

// 1. CABLES INTERNOS DE CONTROL
wire w_ld;
wire w_sh;
wire w_ro;
wire w_nr;
wire w_ld_comp;
wire w_suf;
wire w_z;

// 2. CABLES INTERNOS DE DATOS
wire [31:0] w_resi_out;
wire [31:0] w_subA_out;
wire [31:0] w_comp_out;
wire [31:0] w_comp_shifted;
wire [31:0] w_new_resi;
wire [5:0]  w_out_count;

// 3. LOGICA DE ACOPLAMIENTO
assign w_z = (w_out_count == 6'd0);
assign w_comp_shifted = (w_comp_out << 1) | 32'b1;   // (Comp<<1)+1
assign resi = w_resi_out;

// 4. CONEXION DE MODULOS
control control_unit (
        .clk(clk),
        .rst_hardware(rst_hardware),
        .init(init),
        .suf(w_suf),
        .z(w_z),
        .ld(w_ld),
        .sh(w_sh),
        .ro(w_ro),
        .nr(w_nr),
        .ld_comp(w_ld_comp),
        .done(done_raiz)
    );

resi_subA reg_resiA (
        .clk(clk),
        .ld(w_ld),
        .sh(w_sh),
        .nr(w_nr),
        .radicando(a),
        .new_resi(w_new_resi),
        .resi_out(w_resi_out),
        .subA_out(w_subA_out)
    );

reg_R reg_resultado (
        .clk(clk),
        .ld(w_ld),
        .sh(w_sh),
        .ro(w_ro),
        .R_out(R)
    );

reg_comp reg_comparador (
        .clk(clk),
        .reset(w_ld),
        .ld_comp(w_ld_comp),
        .r_in(R),
        .comp_out(w_comp_out)
    );

sum_C2 restador (
        .resi_in(w_resi_out),
        .term_in(w_comp_shifted),
        .new_resi(w_new_resi),
        .SUF(w_suf)
    );

count contador (
        .clk(clk),
        .ld(w_ld),
        .resta(w_sh),
        .n(6'd16),
        .out_count(w_out_count)
    );

endmodule

Entregas finales/códigos/raizcua/raiz_TB.v
`timescale 1ns/1ps
module raiz_TB; 
reg clk;
reg rst_hardware;
reg init;
reg [31:0] a;
wire [15:0] R;
wire [31:0] resi;
wire done_raiz;

raiz uut (
        .clk(clk),
        .rst_hardware(rst_hardware),
        .init(init),
        .a(a),
        .R(R),
        .resi(resi),
        .done_raiz(done_raiz)
    );

always #5 clk = ~clk;

initial begin
$dumpfile("raiz_TB.vcd");
$dumpvars(0, raiz_TB);

//estado Inicial
        clk = 0;
        rst_hardware = 1; 
        init = 0;
        a = 32'd0;
#20;              
        rst_hardware = 0; 
#10;

// PRUEBA 1: raiz de 20  (4^2=16, resto=4)
        a = 32'd20;  
        init = 1;         
#10;
        init = 0;        
        @(posedge done_raiz);
#10;
$display("PRUEBA 1 -> raiz(%d) = %d, Residuo: %d", a, R, resi);
#40;

// PRUEBA 2: raiz de 1000000  (1000^2=1000000, resto=0)
#40
        a = 32'd1000000;  
#10
        init = 1;         
#10;
        init = 0;   
              
        @(posedge done_raiz);
#10;
$display("PRUEBA 2 -> raiz(%d) = %d, Residuo: %d", a, R, resi);
#40;

$finish;
end
endmodule

Entregas finales/códigos/raizcua/raiz_TB.vcd
$date
	Wed Jul  8 21:57:33 2026
$end
$version
	Icarus Verilog
$end
$timescale
	1ps
$end
$scope module raiz_TB $end
$var wire 32 ! resi [31:0] $end
$var wire 1 " done_raiz $end
$var wire 16 # R [15:0] $end
$var reg 32 $ a [31:0] $end
$var reg 1 % clk $end
$var reg 1 & init $end
$var reg 1 ' rst_hardware $end
$scope module uut $end
$var wire 32 ( a [31:0] $end
$var wire 1 % clk $end
$var wire 1 & init $end
$var wire 32 ) resi [31:0] $end
$var wire 1 ' rst_hardware $end
$var wire 32 * w_comp_shifted [31:0] $end
$var wire 1 + w_z $end
$var wire 1 , w_suf $end
$var wire 32 - w_subA_out [31:0] $end
$var wire 1 . w_sh $end
$var wire 1 / w_ro $end
$var wire 32 0 w_resi_out [31:0] $end
$var wire 6 1 w_out_count [5:0] $end
$var wire 1 2 w_nr $end
$var wire 32 3 w_new_resi [31:0] $end
$var wire 1 4 w_ld_comp $end
$var wire 1 5 w_ld $end
$var wire 32 6 w_comp_out [31:0] $end
$var wire 1 " done_raiz $end
$var wire 16 7 R [15:0] $end
$scope module contador $end
$var wire 1 % clk $end
$var wire 6 8 n [5:0] $end
$var wire 1 . resta $end
$var wire 1 5 ld $end
$var reg 6 9 out_count [5:0] $end
$upscope $end
$scope module control_unit $end
$var wire 1 % clk $end
$var wire 1 & init $end
$var wire 1 ' rst_hardware $end
$var wire 1 + z $end
$var wire 1 , suf $end
$var parameter 3 : CORRER $end
$var parameter 3 ; DONE $end
$var parameter 3 < LD_COMP $end
$var parameter 3 = R_0 $end
$var parameter 3 > START $end
$var parameter 3 ? SUM $end
$var reg 1 " done $end
$var reg 1 5 ld $end
$var reg 1 4 ld_comp $end
$var reg 1 2 nr $end
$var reg 1 / ro $end
$var reg 1 . sh $end
$var reg 3 @ state [2:0] $end
$upscope $end
$scope module reg_comparador $end
$var wire 1 % clk $end
$var wire 1 4 ld_comp $end
$var wire 1 5 reset $end
$var wire 16 A r_in [15:0] $end
$var reg 32 B comp_out [31:0] $end
$upscope $end
$scope module reg_resiA $end
$var wire 1 % clk $end
$var wire 1 5 ld $end
$var wire 1 2 nr $end
$var wire 32 C radicando [31:0] $end
$var wire 1 . sh $end
$var wire 32 D subA_out [31:0] $end
$var wire 32 E resi_out [31:0] $end
$var wire 32 F new_resi [31:0] $end
$var reg 64 G A [63:0] $end
$upscope $end
$scope module reg_resultado $end
$var wire 1 % clk $end
$var wire 1 5 ld $end
$var wire 1 / ro $end
$var wire 1 . sh $end
$var reg 16 H R_out [15:0] $end
$upscope $end
$scope module restador $end
$var wire 1 , SUF $end
$var wire 32 I resi_in [31:0] $end
$var wire 32 J term_in [31:0] $end
$var wire 32 K new_resi [31:0] $end
$upscope $end
$upscope $end
$upscope $end
$enddefinitions $end
$comment Show the parameter values. $end
$dumpall
b11 ?
b0 >
b100 =
b10 <
b101 ;
b1 :
$end
#0
$dumpvars
bx K
bx1 J
bx I
bx H
bx G
bx F
bx E
bx D
b0 C
bx B
bx A
bx @
bx 9
b10000 8
bx 7
bx 6
x5
x4
bx 3
x2
bx 1
bx 0
x/
x.
bx -
x,
x+
bx1 *
bx )
b0 (
1'
0&
0%
b0 $
bx #
x"
bx !
$end
#5000
04
0/
02
15
0.
0"
b0 @
1%
#10000
0,
b11111111111111111111111111111111 3
b11111111111111111111111111111111 F
b11111111111111111111111111111111 K
b1 *
b1 J
b0 !
b0 )
b0 0
b0 E
b0 I
b0 -
b0 D
0+
b10000 1
b10000 9
b0 6
b0 B
b0 #
b0 7
b0 A
b0 H
b0 G
0%
#15000
1%
#20000
0%
0'
#25000
1%
#30000
b10100 -
b10100 D
b10100 G
0%
1&
b10100 $
b10100 (
b10100 C
#35000
05
1.
b1 @
1%
#40000
b1010000 -
b1010000 D
b1010000 G
b1111 1
b1111 9
0%
0&
#45000
14
0.
b10 @
1%
#50000
0%
#55000
04
b100 @
1%
#60000
0%
#65000
1.
b1 @
1%
#70000
b101000000 -
b101000000 D
b1110 1
b1110 9
b101000000 G
0%
#75000
14
0.
b10 @
1%
#80000
0%
#85000
04
b100 @
1%
#90000
0%
#95000
1.
b1 @
1%
#100000
b10100000000 -
b10100000000 D
b10100000000 G
b1101 1
b1101 9
0%
#105000
14
0.
b10 @
1%
#110000
0%
#115000
04
b100 @
1%
#120000
0%
#125000
1.
b1 @
1%
#130000
b1010000000000 -
b1010000000000 D
b1100 1
b1100 9
b1010000000000 G
0%
#135000
14
0.
b10 @
1%
#140000
0%
#145000
04
b100 @
1%
#150000
0%
#155000
1.
b1 @
1%
#160000
b101000000000000 -
b101000000000000 D
b101000000000000 G
b1011 1
b1011 9
0%
#165000
14
0.
b10 @
1%
#170000
0%
#175000
04
b100 @
1%
#180000
0%
#185000
1.
b1 @
1%
#190000
b10100000000000000 -
b10100000000000000 D
b1010 1
b1010 9
b10100000000000000 G
0%
#195000
14
0.
b10 @
1%
#200000
0%
#205000
04
b100 @
1%
#210000
0%
#215000
1.
b1 @
1%
#220000
b1010000000000000000 -
b1010000000000000000 D
b1010000000000000000 G
b1001 1
b1001 9
0%
#225000
14
0.
b10 @
1%
#230000
0%
#235000
04
b100 @
1%
#240000
0%
#245000
1.
b1 @
1%
#250000
b101000000000000000000 -
b101000000000000000000 D
b1000 1
b1000 9
b101000000000000000000 G
0%
#255000
14
0.
b10 @
1%
#260000
0%
#265000
04
b100 @
1%
#270000
0%
#275000
1.
b1 @
1%
#280000
b10100000000000000000000 -
b10100000000000000000000 D
b10100000000000000000000 G
b111 1
b111 9
0%
#285000
14
0.
b10 @
1%
#290000
0%
#295000
04
b100 @
1%
#300000
0%
#305000
1.
b1 @
1%
#310000
b1010000000000000000000000 -
b1010000000000000000000000 D
b110 1
b110 9
b1010000000000000000000000 G
0%
#315000
14
0.
b10 @
1%
#320000
0%
#325000
04
b100 @
1%
#330000
0%
#335000
1.
b1 @
1%
#340000
b101000000000000000000000000 -
b101000000000000000000000000 D
b101000000000000000000000000 G
b101 1
b101 9
0%
#345000
14
0.
b10 @
1%
#350000
0%
#355000
04
b100 @
1%
#360000
0%
#365000
1.
b1 @
1%
#370000
b10100000000000000000000000000 -
b10100000000000000000000000000 D
b100 1
b100 9
b10100000000000000000000000000 G
0%
#375000
14
0.
b10 @
1%
#380000
0%
#385000
04
b100 @
1%
#390000
0%
#395000
1.
b1 @
1%
#400000
b1010000000000000000000000000000 -
b1010000000000000000000000000000 D
b1010000000000000000000000000000 G
b11 1
b11 9
0%
#405000
14
0.
b10 @
1%
#410000
0%
#415000
04
b100 @
1%
#420000
0%
#425000
1.
b1 @
1%
#430000
1,
b0 3
b0 F
b0 K
b1 !
b1 )
b1 0
b1 E
b1 I
b1000000000000000000000000000000 -
b1000000000000000000000000000000 D
b10 1
b10 9
b101000000000000000000000000000000 G
0%
#435000
14
0.
b10 @
1%
#440000
0%
#445000
04
1/
12
b11 @
1%
#450000
0,
b11111111111111111111111111111111 3
b11111111111111111111111111111111 F
b11111111111111111111111111111111 K
b0 !
b0 )
b0 0
b0 E
b0 I
b1 #
b1 7
b1 A
b1 H
b1000000000000000000000000000000 G
0%
#455000
0/
02
1.
b1 @
1%
#460000
1,
b0 3
b0 F
b0 K
b1 !
b1 )
b1 0
b1 E
b1 I
b0 -
b0 D
b100000000000000000000000000000000 G
b10 #
b10 7
b10 A
b10 H
b1 1
b1 9
0%
#465000
14
0.
b10 @
1%
#470000
0,
b11111111111111111111111111111100 3
b11111111111111111111111111111100 F
b11111111111111111111111111111100 K
b101 *
b101 J
b10 6
b10 B
0%
#475000
04
b100 @
1%
#480000
0%
#485000
1.
b1 @
1%
#490000
b11111111111111111111111111111111 3
b11111111111111111111111111111111 F
b11111111111111111111111111111111 K
b100 !
b100 )
b100 0
b100 E
b100 I
1+
b0 1
b0 9
b100 #
b100 7
b100 A
b100 H
b10000000000000000000000000000000000 G
0%
#495000
14
0.
b10 @
1%
#500000
b11111111111111111111111111111011 3
b11111111111111111111111111111011 F
b11111111111111111111111111111011 K
b1001 *
b1001 J
b100 6
b100 B
0%
#505000
04
b100 @
1%
#510000
0%
#515000
1"
b101 @
1%
#520000
0%
#525000
15
0"
b0 @
1%
#530000
b1 *
b1 J
b11111111111111111111111111111111 3
b11111111111111111111111111111111 F
b11111111111111111111111111111111 K
b0 !
b0 )
b0 0
b0 E
b0 I
b10100 -
b10100 D
0+
b10000 1
b10000 9
b0 6
b0 B
b0 #
b0 7
b0 A
b0 H
b10100 G
0%
#535000
1%
#540000
0%
#545000
1%
#550000
0%
#555000
1%
#560000
0%
#565000
1%
#570000
0%
#575000
1%
#580000
0%
#585000
1%
#590000
0%
#595000
1%
#600000
0%
#605000
1%
b11110100001001000000 $
b11110100001001000000 (
b11110100001001000000 C
#610000
b11110100001001000000 -
b11110100001001000000 D
b11110100001001000000 G
0%
#615000
05
1.
b1 @
1%
1&
#620000
b1111010000100100000000 -
b1111010000100100000000 D
b1111010000100100000000 G
b1111 1
b1111 9
0%
#625000
14
0.
b10 @
1%
0&
#630000
0%
#635000
04
b100 @
1%
#640000
0%
#645000
1.
b1 @
1%
#650000
b111101000010010000000000 -
b111101000010010000000000 D
b1110 1
b1110 9
b111101000010010000000000 G
0%
#655000
14
0.
b10 @
1%
#660000
0%
#665000
04
b100 @
1%
#670000
0%
#675000
1.
b1 @
1%
#680000
b11110100001001000000000000 -
b11110100001001000000000000 D
b11110100001001000000000000 G
b1101 1
b1101 9
0%
#685000
14
0.
b10 @
1%
#690000
0%
#695000
04
b100 @
1%
#700000
0%
#705000
1.
b1 @
1%
#710000
b1111010000100100000000000000 -
b1111010000100100000000000000 D
b1100 1
b1100 9
b1111010000100100000000000000 G
0%
#715000
14
0.
b10 @
1%
#720000
0%
#725000
04
b100 @
1%
#730000
0%
#735000
1.
b1 @
1%
#740000
b111101000010010000000000000000 -
b111101000010010000000000000000 D
b111101000010010000000000000000 G
b1011 1
b1011 9
0%
#745000
14
0.
b10 @
1%
#750000
0%
#755000
04
b100 @
1%
#760000
0%
#765000
1.
b1 @
1%
#770000
b11110100001001000000000000000000 -
b11110100001001000000000000000000 D
b1010 1
b1010 9
b11110100001001000000000000000000 G
0%
#775000
14
0.
b10 @
1%
#780000
0%
#785000
04
b100 @
1%
#790000
0%
#795000
1.
b1 @
1%
#800000
1,
b10 3
b10 F
b10 K
b11 !
b11 )
b11 0
b11 E
b11 I
b11010000100100000000000000000000 -
b11010000100100000000000000000000 D
b1111010000100100000000000000000000 G
b1001 1
b1001 9
0%
#805000
14
0.
b10 @
1%
#810000
0%
#815000
04
1/
12
b11 @
1%
#820000
b1 3
b1 F
b1 K
b10 !
b10 )
b10 0
b10 E
b10 I
b1011010000100100000000000000000000 G
b1 #
b1 7
b1 A
b1 H
0%
#825000
0/
02
1.
b1 @
1%
#830000
b1010 3
b1010 F
b1010 K
b1011 !
b1011 )
b1011 0
b1011 E
b1011 I
b1000010010000000000000000000000 -
b1000010010000000000000000000000 D
b1000 1
b1000 9
b10 #
b10 7
b10 A
b10 H
b101101000010010000000000000000000000 G
0%
#835000
14
0.
b10 @
1%
#840000
b110 3
b110 F
b110 K
b101 *
b101 J
b10 6
b10 B
0%
#845000
04
1/
12
b11 @
1%
#850000
b1 3
b1 F
b1 K
b110 !
b110 )
b110 0
b110 E
b110 I
b11 #
b11 7
b11 A
b11 H
b11001000010010000000000000000000000 G
0%
#855000
0/
02
1.
b1 @
1%
#860000
b10100 3
b10100 F
b10100 K
b11001 !
b11001 )
b11001 0
b11001 E
b11001 I
b1001000000000000000000000000 -
b1001000000000000000000000000 D
b1100100001001000000000000000000000000 G
b110 #
b110 7
b110 A
b110 H
b111 1
b111 9
0%
#865000
14
0.
b10 @
1%
#870000
b1100 3
b1100 F
b1100 K
b1101 *
b1101 J
b110 6
b110 B
0%
#875000
04
1/
12
b11 @
1%
#880000
0,
b11111111111111111111111111111111 3
b11111111111111111111111111111111 F
b11111111111111111111111111111111 K
b1100 !
b1100 )
b1100 0
b1100 E
b1100 I
b110000001001000000000000000000000000 G
b111 #
b111 7
b111 A
b111 H
0%
#885000
0/
02
1.
b1 @
1%
#890000
1,
b100011 3
b100011 F
b100011 K
b110000 !
b110000 )
b110000 0
b110000 E
b110000 I
b100100000000000000000000000000 -
b100100000000000000000000000000 D
b110 1
b110 9
b1110 #
b1110 7
b1110 A
b1110 H
b11000000100100000000000000000000000000 G
0%
#895000
14
0.
b10 @
1%
#900000
b10011 3
b10011 F
b10011 K
b11101 *
b11101 J
b1110 6
b1110 B
0%
#905000
04
1/
12
b11 @
1%
#910000
0,
b11111111111111111111111111110110 3
b11111111111111111111111111110110 F
b11111111111111111111111111110110 K
b10011 !
b10011 )
b10011 0
b10011 E
b10011 I
b1111 #
b1111 7
b1111 A
b1111 H
b1001100100100000000000000000000000000 G
0%
#915000
0/
02
1.
b1 @
1%
#920000
1,
b101111 3
b101111 F
b101111 K
b1001100 !
b1001100 )
b1001100 0
b1001100 E
b1001100 I
b10010000000000000000000000000000 -
b10010000000000000000000000000000 D
b100110010010000000000000000000000000000 G
b11110 #
b11110 7
b11110 A
b11110 H
b101 1
b101 9
0%
#925000
14
0.
b10 @
1%
#930000
b1111 3
b1111 F
b1111 K
b111101 *
b111101 J
b11110 6
b11110 B
0%
#935000
04
1/
12
b11 @
1%
#940000
0,
b11111111111111111111111111010010 3
b11111111111111111111111111010010 F
b11111111111111111111111111010010 K
b1111 !
b1111 )
b1111 0
b1111 E
b1111 I
b111110010000000000000000000000000000 G
b11111 #
b11111 7
b11111 A
b11111 H
0%
#945000
0/
02
1.
b1 @
1%
#950000
1,
b1 3
b1 F
b1 K
b111110 !
b111110 )
b111110 0
b111110 E
b111110 I
b1000000000000000000000000000000 -
b1000000000000000000000000000000 D
b100 1
b100 9
b111110 #
b111110 7
b111110 A
b111110 H
b11111001000000000000000000000000000000 G
0%
#955000
14
0.
b10 @
1%
#960000
0,
b11111111111111111111111111000001 3
b11111111111111111111111111000001 F
b11111111111111111111111111000001 K
b1111101 *
b1111101 J
b111110 6
b111110 B
0%
#965000
04
b100 @
1%
#970000
0%
#975000
1.
b1 @
1%
#980000
1,
b1111100 3
b1111100 F
b1111100 K
b11111001 !
b11111001 )
b11111001 0
b11111001 E
b11111001 I
b0 -
b0 D
b1111100100000000000000000000000000000000 G
b1111100 #
b1111100 7
b1111100 A
b1111100 H
b11 1
b11 9
0%
#985000
14
0.
b10 @
1%
#990000
b0 3
b0 F
b0 K
b11111001 *
b11111001 J
b1111100 6
b1111100 B
0%
#995000
04
1/
12
b11 @
1%
#1000000
0,
b11111111111111111111111100000111 3
b11111111111111111111111100000111 F
b11111111111111111111111100000111 K
b0 !
b0 )
b0 0
b0 E
b0 I
b0 G
b1111101 #
b1111101 7
b1111101 A
b1111101 H
0%
#1005000
0/
02
1.
b1 @
1%
#1010000
b10 1
b10 9
b11111010 #
b11111010 7
b11111010 A
b11111010 H
0%
#1015000
14
0.
b10 @
1%
#1020000
b11111111111111111111111000001011 3
b11111111111111111111111000001011 F
b11111111111111111111111000001011 K
b111110101 *
b111110101 J
b11111010 6
b11111010 B
0%
#1025000
04
b100 @
1%
#1030000
0%
#1035000
1.
b1 @
1%
#1040000
b111110100 #
b111110100 7
b111110100 A
b111110100 H
b1 1
b1 9
0%
#1045000
14
0.
b10 @
1%
#1050000
b11111111111111111111110000010111 3
b11111111111111111111110000010111 F
b11111111111111111111110000010111 K
b1111101001 *
b1111101001 J
b111110100 6
b111110100 B
0%
#1055000
04
b100 @
1%
#1060000
0%
#1065000
1.
b1 @
1%
#1070000
1+
b0 1
b0 9
b1111101000 #
b1111101000 7
b1111101000 A
b1111101000 H
0%
#1075000
14
0.
b10 @
1%
#1080000
b11111111111111111111100000101111 3
b11111111111111111111100000101111 F
b11111111111111111111100000101111 K
b11111010001 *
b11111010001 J
b1111101000 6
b1111101000 B
0%
#1085000
04
b100 @
1%
#1090000
0%
#1095000
1"
b101 @
1%
#1100000
0%
#1105000
15
0"
b0 @
1%
#1110000
b11111111111111111111111111111111 3
b11111111111111111111111111111111 F
b11111111111111111111111111111111 K
b1 *
b1 J
b11110100001001000000 -
b11110100001001000000 D
0+
b10000 1
b10000 9
b0 6
b0 B
b0 #
b0 7
b0 A
b0 H
b11110100001001000000 G
0%
