Entregas finales/códigos/bin2bcd/comp2.v
module comp2(
    input [6:0] num, 
    output reg z     
);

always @(*) begin
    if (num == 7'b0) begin
        z = 1'b1; 
    end
    else begin
        z = 1'b0; 
    end
end

endmodule

Entregas finales/códigos/bin2bcd/comp.v
module comp(
    input [3:0] U,
    input [3:0] D,
    input comp_U, 
    input comp_D, 
    output reg x1, //unidades
    output reg x2  //decenas
);

always @(*) begin
    // Lógica para evaluar las Unidades
    if (comp_U) begin
        x1 = (U >= 4'd5) ? 1'b1 : 1'b0;
    end
    else begin
        x1 = 1'b0;
    end

    // Lógica para evaluar las Decenas
    if (comp_D) begin
        x2 = (D >= 4'd5) ? 1'b1 : 1'b0;
    end
    else begin
        x2 = 1'b0; 
    end
end

endmodule

Entregas finales/códigos/bin2bcd/sum.v
module sum(
    input [3:0] U,
    input [3:0] D,
    input R_U,  
    input R_D,  
    output reg [3:0] out_new_U,
    output reg [3:0] out_new_D
);

always @(*) begin
   
    if (R_U) begin
        out_new_U = U + 4'd3;
    end
    else begin
        out_new_U = U;
    end

   
    if (R_D) begin
        out_new_D = D + 4'd3;
    end
    else begin
        out_new_D = D;
    end
end

endmodule

Entregas finales/códigos/bin2bcd/reg_numBCD.v
module reg_numBCD(
    input clk,
    input ld,
    input sh,
    input new_U,
    input new_D,
    input  [6:0] A,
    input  [3:0] new_U_val,   
    input  [3:0] new_D_val,   
    output [3:0] D,      // ¡Ojo! Quitamos el 'reg' aquí porque ahora son asignaciones continuas
    output [3:0] U,      // Quitamos el 'reg'
    output [6:0] num     // Quitamos el 'reg'
);

    // 1. Creación del registro gigante de 15 bits
    reg [14:0] num_bcd;

    // 2. Extracción de las salidas (Asignación continua como en tu divisor)
    assign D   = num_bcd[14:11]; // Los 4 bits más altos
    assign U   = num_bcd[10:7];  // Los 4 bits del medio
    assign num = num_bcd[6:0];   // Los 7 bits más bajos

    // 3. Lógica secuencial
    always @(negedge clk) begin
        if (ld) begin
            // Cargamos 8 ceros (para D y U) concatenados con el número A
            num_bcd <= {8'd0, A};
        end
        else if (sh) begin
            // ¡El desplazamiento ahora es súper fácil y en una sola línea!
            num_bcd <= {num_bcd[13:0], 1'b0};
        end
        else begin
            // Sobreescritura parcial directa en los "cajones" correspondientes
            if (new_U) begin
                num_bcd[10:7] <= new_U_val;
            end
            if (new_D) begin
                num_bcd[14:11] <= new_D_val;
            end
        end
    end

endmodule

Entregas finales/códigos/bin2bcd/control.v
module control (
    input clk,
    input rst_hardware, 
    input init,
    input x1,      // Viene del comparador: Indica si U >= 5
    input x2,      // Viene del comparador: Indica si D >= 5
    input z,       // Viene de comp_2: Indica si el número binario ya es cero
    output reg ld,
    output reg sh,
    output reg new_U,
    output reg new_D,
    output reg comp_U,
    output reg comp_D,
    output reg done
);

    // Definición de los estados
    reg [3:0] state;

    localparam START   = 4'd0,
               LOAD    = 4'd1,
               CHECK_U = 4'd2,
               ADD_U   = 4'd3,
               CHECK_D = 4'd4,
               ADD_D   = 4'd5,
               SHIFT_A = 4'd6,
               CHECK_Z = 4'd7,
               DONE    = 4'd8;

// 1. Bloque secuencial: Transición de estados
always @(posedge clk) begin
    if (rst_hardware) begin
        state <= START;
    end else begin
        case(state)

        START: begin
            if(init)
                state <= LOAD;
            else
                state <= START;
        end

        LOAD: begin
            state <= SHIFT_A;
        end

        SHIFT_A: begin
            state <= CHECK_Z;
        end

        CHECK_Z: begin
            
            if (z)
                state <= DONE;
            else
                state <= CHECK_U;
        end


        CHECK_U: begin
            
            if (x1)
                state <= ADD_U;
            else
                state <= CHECK_D;
        end

        ADD_U: begin
            state <= CHECK_D;
        end

        CHECK_D: begin
            // Si las decenas son >= 5, vamos a sumarles 3
            if (x2)
                state <= ADD_D;
            else
                state <= SHIFT_A;
        end

        ADD_D: begin
            state <= SHIFT_A;
        end

        

        
        DONE: begin
                state <= START;
        end
        
        default: state <= START;
        
        endcase
    end
end

// 2. Bloque combinacional
always @(state) begin
    case(state)

        START: begin
            ld = 0;
            sh = 0;
            new_U = 0;
            new_D = 0;
            comp_U = 0;
            comp_D = 0;
            done = 0;
        end

        LOAD: begin
            ld = 1;
            sh = 0;
            new_U = 0;
            new_D = 0;
            comp_U = 0;
            comp_D = 0;
            done = 0;
        end

        SHIFT_A: begin
            ld = 0;
            sh = 1;    
            new_U = 0;
            new_D = 0;
            comp_U = 0;
            comp_D = 0;
            done = 0;
        end


        CHECK_Z: begin
            ld = 0;
            sh = 0;
            new_U = 0;
            new_D = 0;
            comp_U = 0;
            comp_D = 0;
            done = 0;
        end

        CHECK_U: begin
            ld = 0;
            sh = 0;
            new_U = 0;
            new_D = 0;
            comp_U = 1; 
            comp_D = 0;
            done = 0;
        end

        ADD_U: begin
            ld = 0;
            sh = 0;
            new_U = 1;  
            new_D = 0;
            comp_U = 0;
            comp_D = 0;
            done = 0;
        end

        CHECK_D: begin
            ld = 0;
            sh = 0;
            new_U = 0;
            new_D = 0;
            comp_U = 0;
            comp_D = 1; 
            done = 0;
        end

        ADD_D: begin
            ld = 0;
            sh = 0;
            new_U = 0;
            new_D = 1;
            comp_U = 0;
            comp_D = 0;
            done = 0;
        end
        

        DONE: begin
            ld = 0;
            sh = 0;
            new_U = 0;
            new_D = 0;
            comp_U = 0;
            comp_D = 0;
            done = 1;   
        end

        default: begin
            ld = 0;
            sh = 0;
            new_U = 0;
            new_D = 0;
            comp_U = 0;
            comp_D = 0;
            done = 0;
        end

    endcase
end

endmodule

Entregas finales/códigos/bin2bcd/bin2bcd.v
module bin2bcd(
    input clk,
    input rst_hardware,
    input init,
    input [6:0] A,
    output [3:0] U,
    output [3:0] D,
    output done
);

    // ==========================================
    // 1. CABLES INTERNOS DE CONTROL
    // ==========================================
    wire w_ld;
    wire w_sh;
    wire w_new_U;
    wire w_new_D;
    wire w_comp_U;
    wire w_comp_D;
    wire w_x1;
    wire w_x2;
    wire w_z;

    // ==========================================
    // 2. CABLES INTERNOS DE DATOS
    // ==========================================
    wire [3:0] w_new_U_val;
    wire [3:0] w_new_D_val;
    wire [6:0] w_num;

    // ==========================================
    // 3. LÓGICA DE ACOPLAMIENTO
    // ==========================================
    // (En este caso particular, las salidas U y D 
    // se conectan directamente a los puertos del registro, 
    // así que no necesitamos assigns extra).

    // ==========================================
    // 4. CONEXIÓN DE MÓDULOS
    // ==========================================

    // Unidad de Control (FSM)
    control control_unit (
        .clk(clk),
        .rst_hardware(rst_hardware),
        .init(init),
        .x1(w_x1),
        .x2(w_x2),
        .z(w_z),
        .ld(w_ld),
        .sh(w_sh),
        .new_U(w_new_U),
        .new_D(w_new_D),
        .comp_U(w_comp_U),
        .comp_D(w_comp_D),
        .done(done)
    );

    // Registro Principal BCD
    reg_numBCD datapath_reg (
        .clk(clk),
        .ld(w_ld),
        .sh(w_sh),
        .new_U(w_new_U),
        .new_D(w_new_D),
        .A(A),
        .new_U_val(w_new_U_val),
        .new_D_val(w_new_D_val),
        .D(D),     // Conexión directa a la salida del módulo general
        .U(U),     // Conexión directa a la salida del módulo general
        .num(w_num)
    );

    // Sumador Combinacional
    sum sumador (
        .U(U),
        .D(D),
        .R_U(w_new_U),
        .R_D(w_new_D),
        .out_new_U(w_new_U_val),
        .out_new_D(w_new_D_val)
    );

    // Comparador Combinacional (>= 5)
    comp comparador_5 (
        .U(U),
        .D(D),
        .comp_U(w_comp_U),
        .comp_D(w_comp_D),
        .x1(w_x1),
        .x2(w_x2)
    );

    // Comparador de Cero
    comp2 comparador_z (
        .num(w_num),
        .z(w_z)
    );

endmodule

Entregas finales/códigos/bin2bcd/bin2bcd_TB.v
`timescale 1ns / 1ps
`define SIMULATION

module bin2bcd_TB;

  // Entradas de la caja negra
  reg clk;
  reg rst_hardware;
  reg init;
  reg [6:0] A;

  // Salidas de la caja negra
  wire [3:0] U;
  wire [3:0] D;
  wire done;

  // Instanciación del módulo contenedor
  bin2bcd uut (
      .clk(clk),
      .rst_hardware(rst_hardware),
      .init(init),
      .A(A),
      .U(U),
      .D(D),
      .done(done)
  );

  parameter PERIOD          = 20;
  parameter real DUTY_CYCLE = 0.5;
  parameter OFFSET          = 0;

  // Generador automático de Reloj
  initial begin
    #OFFSET;
    forever begin
        clk = 1'b0;
        #(PERIOD-(PERIOD*DUTY_CYCLE)) clk = 1'b1;
        #(PERIOD*DUTY_CYCLE);
    end
  end

  // Secuencia de estimulación automática
  // Secuencia de estimulación automática (CORREGIDA)
  initial begin
    // 1. Estado de Reset inicial
    #0 rst_hardware = 1; init = 0; A = 7'd0;
    
    // Soltamos el reset en el flanco de bajada
    @(negedge clk);
    rst_hardware = 0;
    
    // 2. Cargar número a convertir (ej. 67 decimal = 1000011 binario)
    @(negedge clk);
    A = 7'd67;  
    init = 1;   // Le damos el pulso de arranque
    
    // Lo soltamos en el siguiente flanco de bajada
    @(negedge clk);
    init = 0;   
    
    // Dejamos que el sistema haga todos los desplazamientos por sí solo.
    wait(done == 1'b1);
    
    // Tiempo para apreciar el resultado (Debe salir D=6 y U=7)
    #(50);

    // 3. Nueva conversión (ej. 45 decimal)
    @(negedge clk);
    A = 7'd45;
    init = 1;
    
    @(negedge clk);
    init = 0;
    
    wait(done == 1'b1);
    
    // Tiempo final
    #(120);
  end

  // Configuración del GTKWave
  initial begin: TEST_CASE
     $dumpfile("bin2bcd_TB.vcd");
     $dumpvars(-1, uut);
     #(2000) $finish; 
  end

endmodule

Entregas finales/códigos/bin2bcd/bin2bcd_TB.vcd
$date
	Mon Jul 13 15:34:11 2026
$end
$version
	Icarus Verilog
$end
$timescale
	1ps
$end
$scope module bin2bcd_TB $end
$scope module uut $end
$var wire 7 ! A [6:0] $end
$var wire 1 " clk $end
$var wire 1 # init $end
$var wire 1 $ rst_hardware $end
$var wire 1 % w_z $end
$var wire 1 & w_x2 $end
$var wire 1 ' w_x1 $end
$var wire 1 ( w_sh $end
$var wire 7 ) w_num [6:0] $end
$var wire 4 * w_new_U_val [3:0] $end
$var wire 1 + w_new_U $end
$var wire 4 , w_new_D_val [3:0] $end
$var wire 1 - w_new_D $end
$var wire 1 . w_ld $end
$var wire 1 / w_comp_U $end
$var wire 1 0 w_comp_D $end
$var wire 1 1 done $end
$var wire 4 2 U [3:0] $end
$var wire 4 3 D [3:0] $end
$scope module comparador_5 $end
$var wire 1 / comp_U $end
$var wire 1 0 comp_D $end
$var wire 4 4 U [3:0] $end
$var wire 4 5 D [3:0] $end
$var reg 1 ' x1 $end
$var reg 1 & x2 $end
$upscope $end
$scope module comparador_z $end
$var wire 7 6 num [6:0] $end
$var reg 1 % z $end
$upscope $end
$scope module control_unit $end
$var wire 1 " clk $end
$var wire 1 # init $end
$var wire 1 $ rst_hardware $end
$var wire 1 ' x1 $end
$var wire 1 & x2 $end
$var wire 1 % z $end
$var parameter 4 7 ADD_D $end
$var parameter 4 8 ADD_U $end
$var parameter 4 9 CHECK_D $end
$var parameter 4 : CHECK_U $end
$var parameter 4 ; CHECK_Z $end
$var parameter 4 < DONE $end
$var parameter 4 = LOAD $end
$var parameter 4 > SHIFT_A $end
$var parameter 4 ? START $end
$var reg 1 0 comp_D $end
$var reg 1 / comp_U $end
$var reg 1 1 done $end
$var reg 1 . ld $end
$var reg 1 - new_D $end
$var reg 1 + new_U $end
$var reg 1 ( sh $end
$var reg 4 @ state [3:0] $end
$upscope $end
$scope module datapath_reg $end
$var wire 7 A A [6:0] $end
$var wire 1 " clk $end
$var wire 1 . ld $end
$var wire 1 - new_D $end
$var wire 1 + new_U $end
$var wire 1 ( sh $end
$var wire 7 B num [6:0] $end
$var wire 4 C new_U_val [3:0] $end
$var wire 4 D new_D_val [3:0] $end
$var wire 4 E U [3:0] $end
$var wire 4 F D [3:0] $end
$var reg 15 G num_bcd [14:0] $end
$upscope $end
$scope module sumador $end
$var wire 4 H D [3:0] $end
$var wire 1 - R_D $end
$var wire 1 + R_U $end
$var wire 4 I U [3:0] $end
$var reg 4 J out_new_D [3:0] $end
$var reg 4 K out_new_U [3:0] $end
$upscope $end
$upscope $end
$upscope $end
$enddefinitions $end
$comment Show the parameter values. $end
$dumpall
b0 ?
b110 >
b1 =
b1000 <
b111 ;
b10 :
b100 9
b11 8
b101 7
$end
#0
$dumpvars
bx K
bx J
bx I
bx H
bx G
bx F
bx E
bx D
bx C
bx B
b0 A
bx @
bx 6
bx 5
bx 4
bx 3
bx 2
x1
x0
x/
x.
x-
bx ,
x+
bx *
bx )
x(
x'
x&
x%
1$
0#
0"
b0 !
$end
#10000
0&
0'
01
00
0/
0-
0+
0(
0.
b0 @
1"
#20000
0$
0"
#30000
1"
#40000
1#
b1000011 !
b1000011 A
0"
#50000
1.
b1 @
1"
#60000
b0 ,
b0 D
b0 J
b0 *
b0 C
b0 K
0%
b0 3
b0 5
b0 F
b0 H
b0 2
b0 4
b0 E
b0 I
b1000011 )
b1000011 6
b1000011 B
b1000011 G
0#
0"
#70000
1(
0.
b110 @
1"
#80000
b1 *
b1 C
b1 K
b1 2
b1 4
b1 E
b1 I
b110 )
b110 6
b110 B
b10000110 G
0"
#90000
0(
b111 @
1"
#100000
0"
#110000
1/
b10 @
1"
#120000
0"
#130000
10
0/
b100 @
1"
#140000
0"
#150000
00
1(
b110 @
1"
#160000
b10 *
b10 C
b10 K
b10 2
b10 4
b10 E
b10 I
b1100 )
b1100 6
b1100 B
b100001100 G
0"
#170000
0(
b111 @
1"
#180000
0"
#190000
1/
b10 @
1"
#200000
0"
#210000
10
0/
b100 @
1"
#220000
0"
#230000
00
1(
b110 @
1"
#240000
b100 *
b100 C
b100 K
b100 2
b100 4
b100 E
b100 I
b11000 )
b11000 6
b11000 B
b1000011000 G
0"
#250000
0(
b111 @
1"
#260000
0"
#270000
1/
b10 @
1"
#280000
0"
#290000
10
0/
b100 @
1"
#300000
0"
#310000
00
1(
b110 @
1"
#320000
b1000 *
b1000 C
b1000 K
b1000 2
b1000 4
b1000 E
b1000 I
b110000 )
b110000 6
b110000 B
b10000110000 G
0"
#330000
0(
b111 @
1"
#340000
0"
#350000
1'
1/
b10 @
1"
#360000
0"
#370000
0'
b1011 *
b1011 C
b1011 K
0/
1+
b11 @
1"
#380000
b1110 *
b1110 C
b1110 K
b1011 2
b1011 4
b1011 E
b1011 I
b10110110000 G
0"
#390000
b1011 *
b1011 C
b1011 K
10
0+
b100 @
1"
#400000
0"
#410000
00
1(
b110 @
1"
#420000
b1 ,
b1 D
b1 J
b110 *
b110 C
b110 K
b1 3
b1 5
b1 F
b1 H
b110 2
b110 4
b110 E
b110 I
b1100000 )
b1100000 6
b1100000 B
b101101100000 G
0"
#430000
0(
b111 @
1"
#440000
0"
#450000
1'
1/
b10 @
1"
#460000
0"
#470000
0'
b1001 *
b1001 C
b1001 K
0/
1+
b11 @
1"
#480000
b1100 *
b1100 C
b1100 K
b1001 2
b1001 4
b1001 E
b1001 I
b110011100000 G
0"
#490000
b1001 *
b1001 C
b1001 K
10
0+
b100 @
1"
#500000
0"
#510000
00
1(
b110 @
1"
#520000
b11 ,
b11 D
b11 J
b11 *
b11 C
b11 K
b11 3
b11 5
b11 F
b11 H
b11 2
b11 4
b11 E
b11 I
b1000000 )
b1000000 6
b1000000 B
b1100111000000 G
0"
#530000
0(
b111 @
1"
#540000
0"
#550000
1/
b10 @
1"
#560000
0"
#570000
10
0/
b100 @
1"
#580000
0"
#590000
00
1(
b110 @
1"
#600000
b110 ,
b110 D
b110 J
b111 *
b111 C
b111 K
1%
b110 3
b110 5
b110 F
b110 H
b111 2
b111 4
b111 E
b111 I
b0 )
b0 6
b0 B
b11001110000000 G
0"
#610000
0(
b111 @
1"
#620000
0"
#630000
11
b1000 @
1"
#640000
0"
#650000
01
b0 @
1"
#660000
0"
#670000
1"
#680000
1#
b101101 !
b101101 A
0"
#690000
1.
b1 @
1"
#700000
b0 ,
b0 D
b0 J
b0 *
b0 C
b0 K
0%
b0 3
b0 5
b0 F
b0 H
b0 2
b0 4
b0 E
b0 I
b101101 )
b101101 6
b101101 B
b101101 G
0#
0"
#710000
1(
0.
b110 @
1"
#720000
b1011010 )
b1011010 6
b1011010 B
b1011010 G
0"
#730000
0(
b111 @
1"
#740000
0"
#750000
1/
b10 @
1"
#760000
0"
#770000
10
0/
b100 @
1"
#780000
0"
#790000
00
1(
b110 @
1"
#800000
b1 *
b1 C
b1 K
b1 2
b1 4
b1 E
b1 I
b110100 )
b110100 6
b110100 B
b10110100 G
0"
#810000
0(
b111 @
1"
#820000
0"
#830000
1/
b10 @
1"
#840000
0"
#850000
10
0/
b100 @
1"
#860000
0"
#870000
00
1(
b110 @
1"
#880000
b10 *
b10 C
b10 K
b10 2
b10 4
b10 E
b10 I
b1101000 )
b1101000 6
b1101000 B
b101101000 G
0"
#890000
0(
b111 @
1"
#900000
0"
#910000
1/
b10 @
1"
#920000
0"
#930000
10
0/
b100 @
1"
#940000
0"
#950000
00
1(
b110 @
1"
#960000
b101 *
b101 C
b101 K
b101 2
b101 4
b101 E
b101 I
b1010000 )
b1010000 6
b1010000 B
b1011010000 G
0"
#970000
0(
b111 @
1"
#980000
0"
#990000
1'
1/
b10 @
1"
#1000000
0"
#1010000
0'
b1000 *
b1000 C
b1000 K
0/
1+
b11 @
1"
#1020000
b1011 *
b1011 C
b1011 K
b1000 2
b1000 4
b1000 E
b1000 I
b10001010000 G
0"
#1030000
b1000 *
b1000 C
b1000 K
10
0+
b100 @
1"
#1040000
0"
#1050000
00
1(
b110 @
1"
#1060000
b1 ,
b1 D
b1 J
b1 *
b1 C
b1 K
b1 3
b1 5
b1 F
b1 H
b1 2
b1 4
b1 E
b1 I
b100000 )
b100000 6
b100000 B
b100010100000 G
0"
#1070000
0(
b111 @
1"
#1080000
0"
#1090000
1/
b10 @
1"
#1100000
0"
#1110000
10
0/
b100 @
1"
#1120000
0"
#1130000
00
1(
b110 @
1"
#1140000
b10 ,
b10 D
b10 J
b10 *
b10 C
b10 K
b10 3
b10 5
b10 F
b10 H
b10 2
b10 4
b10 E
b10 I
b1000000 )
b1000000 6
b1000000 B
b1000101000000 G
0"
#1150000
0(
b111 @
1"
#1160000
0"
#1170000
1/
b10 @
1"
#1180000
0"
#1190000
10
0/
b100 @
1"
#1200000
0"
#1210000
00
1(
b110 @
1"
#1220000
b100 ,
b100 D
b100 J
b101 *
b101 C
b101 K
1%
b100 3
b100 5
b100 F
b100 H
b101 2
b101 4
b101 E
b101 I
b0 )
b0 6
b0 B
b10001010000000 G
0"
#1230000
0(
b111 @
1"
#1240000
0"
#1250000
11
b1000 @
1"
#1260000
0"
#1270000
01
b0 @
1"
