Entregas finales/códigos/bcd2bin/i.v
module i (

    input clk,
    input ld,
    input resta,
    input [5:0] n,

    output reg [5:0] out_i

);

always @(negedge clk) begin

    if(ld)
        out_i <= n;

    else if(resta)
        out_i <= out_i - 1;

    else
        out_i <= out_i;

end

endmodule

Entregas finales/códigos/bcd2bin/val_error.v
module val_error(
    input  [3:0] A,   // decenas
    input  [3:0] B,   // unidades
    output Error
);

wire Error1;
wire Error2;

assign Error1 = A[3] & (A[2] | A[1]);
assign Error2 = B[3] & (B[2] | B[1]);
assign Error  = Error1 | Error2;

endmodule

Entregas finales/códigos/bcd2bin/sumadorC2.v
module sumadorC2 (
    input [3:0] out_D,
    input [3:0] out_U,
    input new_D,
    input new_U,
    output reg [3:0] out_new_D,
    output reg [3:0] out_new_U
);

always @(*) begin

    if (new_U) begin
        out_new_U = out_U - 4'd3;
    end
    else begin
        out_new_U = out_U;
    end


    if (new_D) begin
        out_new_D = out_D - 4'd3;
    end
    else begin
        out_new_D = out_D;
    end
end

endmodule

Entregas finales/códigos/bcd2bin/comp.v
module comp(
    input [3:0] U,
    input [3:0] D,
    input comp_U, 
    input comp_D, 
    output reg x1, //unidades
    output reg x2  //decenas
);
always @(*) begin
    // Logica para evaluar las Unidades
    if (comp_U) begin
        x1 = (U >= 4'd8) ? 1'b1 : 1'b0;
    end
    else begin
        x1 = 1'b0;
    end
    // Logica para evaluar las Decenas
    if (comp_D) begin
        x2 = (D >= 4'd8) ? 1'b1 : 1'b0;
    end
    else begin
        x2 = 1'b0; 
    end
end
endmodule

Entregas finales/códigos/bcd2bin/reg_DUnum.v
module reg_DUnum(
    input clk,
    input ld,
    input sh,
    input new_U,
    input new_D,
    input  [3:0] A,           // decenas (BCD)
    input  [3:0] B,           // unidades (BCD)
    input  [3:0] new_U_val,   // viene de sum_C2 (U-3)
    input  [3:0] new_D_val,   // viene de sum_C2 (D-3)
    output [3:0] D,
    output [3:0] U,
    output [6:0] num
);
    // 1. Creacion del registro gigante de 15 bits
    reg [14:0] num_bcd;

    // 2. Extraccion de las salidas (asignacion continua)
    assign D   = num_bcd[14:11]; // Los 4 bits mas altos
    assign U   = num_bcd[10:7];  // Los 4 bits del medio
    assign num = num_bcd[6:0];   // Los 7 bits mas bajos

    // 3. Logica secuencial
    always @(negedge clk) begin
        if (ld) begin
            // Cargamos A y B en D y U, y 7 ceros en num
            num_bcd <= {A, B, 7'd0};
        end
        else if (sh) begin
            // Shift a la DERECHA, entra un 0 por el bit mas alto
            num_bcd <= {1'b0, num_bcd[14:1]};
        end
        else begin
            // Sobreescritura parcial directa en los "cajones" correspondientes
            if (new_U) begin
                num_bcd[10:7] <= new_U_val;
            end
            if (new_D) begin
                num_bcd[14:11] <= new_D_val;
            end
        end
    end
endmodule

Entregas finales/códigos/bcd2bin/control.v
module control (
    input clk,
    input rst_hardware,
    input init,
    input error,
    input x1,      // U >= 8
    input x2,      // D >= 8
    input z,       // i == 0
    output reg ld,
    output reg sh,
    output reg comp_U,
    output reg comp_D,
    output reg new_U,
    output reg new_D,
    output reg done
);

reg [3:0] state;
localparam START   = 4'b0000,
           SH       = 4'b0001,
           CHECK_1  = 4'b0010,
           CHECK_U  = 4'b0011,
           SUM_U    = 4'b0100,
           CHECK_D  = 4'b0101,
           SUM_D    = 4'b0110,
           DONE     = 4'b0111;

// 1. Bloque secuencial: Transicion de estados
always @(posedge clk) begin
    if (rst_hardware) begin
        state <= START;
    end else begin
        case(state)
            START: begin
                if (init && !error)
                    state <= SH;
                else
                    state <= START;
            end
            SH: begin
                state <= CHECK_1;
            end
            CHECK_1: begin
                if (z)
                    state <= DONE;
                else
                    state <= CHECK_U;
            end
            CHECK_U: begin
                if (x1)
                    state <= SUM_U;
                else
                    state <= CHECK_D;
            end
            SUM_U: begin
                state <= CHECK_D;
            end
            CHECK_D: begin
                if (x2)
                    state <= SUM_D;
                else
                    state <= SH;
            end
            SUM_D: begin
                state <= SH;
            end
            DONE: begin
                    state <= START;
            end
            default: state <= START;
        endcase
    end
end

// 2. Bloque combinacional: Salidas de control segun el estado
always @(*) begin
    case(state)
        START:begin
            ld=1; 
            sh=0; 
            comp_U=0; 
            comp_D=0; 
            new_U=0; 
            new_D=0; 
            done=0;
        end
        SH:begin 
            ld=0;
            sh=1;
            comp_U=0;
            comp_D=0;
            new_U=0;
            new_D=0;
            done=0;
        end
        CHECK_1:
        begin
            ld=0;
            sh=0;
            comp_U=0;
            comp_D=0;
            new_U=0;
            new_D=0;
            done=0;
        end

        CHECK_U:begin
            ld=0;
            sh=0;
            comp_U=1;
            comp_D=0;
            new_U=0;
            new_D=0;
            done=0;
        end

        SUM_U:begin
            ld=0;
            sh=0;
            comp_U=0;
            comp_D=0;
            new_U=1;
            new_D=0;
            done=0;
        end
        
        CHECK_D:begin
            ld=0;
            sh=0;
            comp_U=0;
            comp_D=1;
            new_U=0;
            new_D=0;
            done=0;
        end
        
        SUM_D:begin
            ld=0;
            sh=0;
            comp_U=0;
            comp_D=0;
            new_U=0;
            new_D=1;
            done=0;
        end
        
        DONE:begin
            ld=0;
            sh=0;
            comp_U=0;
            comp_D=0;
            new_U=0;
            new_D=0;
            done=1;
        end
        default:begin 
            ld=0;
            sh=0;
            comp_U=0;
            comp_D=0;
            new_U=0;
            new_D=0;
            done=0;
        end
    endcase
end

endmodule

Entregas finales/códigos/bcd2bin/bcd2bin.v
module bcd2bin(
    input clk,
    input rst_hardware,
    input init,
    input  [3:0] A,        // decenas (BCD)
    input  [3:0] B,        // unidades (BCD)
    output [6:0] num_bin,  // resultado binario
    output done
);

// 1. CABLES INTERNOS DE CONTROL
wire w_ld;
wire w_sh;
wire w_comp_U;
wire w_comp_D;
wire w_new_U;
wire w_new_D;
wire w_x1;
wire w_x2;
wire w_z;
wire w_error;

// 2. CABLES INTERNOS DE DATOS
wire [3:0] w_D;
wire [3:0] w_U;
wire [3:0] w_new_U_val;
wire [3:0] w_new_D_val;
wire [5:0] w_out_count;

// 3. LOGICA DE ACOPLAMIENTO
assign w_z = (w_out_count == 6'd0);

// 4. CONEXION DE MODULOS
control control_unit (
    .clk(clk),
    .rst_hardware(rst_hardware),
    .init(init),
    .error(w_error),
    .x1(w_x1),
    .x2(w_x2),
    .z(w_z),
    .ld(w_ld),
    .sh(w_sh),
    .comp_U(w_comp_U),
    .comp_D(w_comp_D),
    .new_U(w_new_U),
    .new_D(w_new_D),
    .done(done)
);

reg_DUnum reg_datos (
    .clk(clk),
    .ld(w_ld),
    .sh(w_sh),
    .new_U(w_new_U),
    .new_D(w_new_D),
    .A(A),
    .B(B),
    .new_U_val(w_new_U_val),
    .new_D_val(w_new_D_val),
    .D(w_D),
    .U(w_U),
    .num(num_bin)
);

comp comparador (
    .U(w_U),
    .D(w_D),
    .comp_U(w_comp_U),
    .comp_D(w_comp_D),
    .x1(w_x1),
    .x2(w_x2)
);

sumadorC2 restador (
    .out_D(w_D),
    .out_U(w_U),
    .new_D(w_new_D),
    .new_U(w_new_U),
    .out_new_D(w_new_D_val),
    .out_new_U(w_new_U_val)
);

val_error validador (
    .A(A),
    .B(B),
    .Error(w_error)
);

i contador (
    .clk(clk),
    .ld(w_ld),
    .resta(w_sh),
    .n(6'd7),
    .out_i(w_out_count)
);

endmodule

Entregas finales/códigos/bcd2bin/bcd2bin_TB.v
`timescale 1ns/1ps

module bcd2bin_TB;
reg clk;
reg rst_hardware;
reg init;
reg [3:0] A;
reg [3:0] B;
wire [6:0] num_bin;
wire done;

bcd2bin uut (
        .clk(clk),
        .rst_hardware(rst_hardware),
        .init(init),
        .A(A),
        .B(B),
        .num_bin(num_bin),
        .done(done)
    );

always #5 clk = ~clk;

initial begin
$dumpfile("bcd2bin_TB.vcd");
$dumpvars(0, bcd2bin_TB);

//estado Inicial
        clk = 0;
        rst_hardware = 1;
        init = 0;
        A = 4'd0;
        B = 4'd0;
#20;

        rst_hardware = 0;
#10;

// PRUEBA 1: BCD 45 (A=4, B=5) -> esperado 45 decimal (0101101)
        A = 4'd4;
        B = 4'd5;
        init = 1;
#11;
        init = 0;

        @(posedge done);
#11;
$display("PRUEBA 1 -> BCD %0d%0d = %d (bin: %b)", A, B, num_bin, num_bin);
#41;

// PRUEBA 2: BCD 99 (A=9, B=9) -> esperado 99 decimal (1100011)
        A = 4'd9;
        B = 4'd9;
        init = 1;
#11;
        init = 0;

        @(posedge done);
#11;
$display("PRUEBA 2 -> BCD %0d%0d = %d (bin: %b)", A, B, num_bin, num_bin);
#41;

$finish;
end

endmodule

Entregas finales/códigos/bcd2bin/bcd2bin_TB.vcd
$date
	Mon Jul 13 19:38:43 2026
$end
$version
	Icarus Verilog
$end
$timescale
	1ps
$end
$scope module bcd2bin_TB $end
$var wire 7 ! num_bin [6:0] $end
$var wire 1 " done $end
$var reg 4 # A [3:0] $end
$var reg 4 $ B [3:0] $end
$var reg 1 % clk $end
$var reg 1 & init $end
$var reg 1 ' rst_hardware $end
$scope module uut $end
$var wire 4 ( A [3:0] $end
$var wire 4 ) B [3:0] $end
$var wire 1 % clk $end
$var wire 1 & init $end
$var wire 1 ' rst_hardware $end
$var wire 1 * w_z $end
$var wire 1 + w_x2 $end
$var wire 1 , w_x1 $end
$var wire 1 - w_sh $end
$var wire 6 . w_out_count [5:0] $end
$var wire 4 / w_new_U_val [3:0] $end
$var wire 1 0 w_new_U $end
$var wire 4 1 w_new_D_val [3:0] $end
$var wire 1 2 w_new_D $end
$var wire 1 3 w_ld $end
$var wire 1 4 w_error $end
$var wire 1 5 w_comp_U $end
$var wire 1 6 w_comp_D $end
$var wire 4 7 w_U [3:0] $end
$var wire 4 8 w_D [3:0] $end
$var wire 7 9 num_bin [6:0] $end
$var wire 1 " done $end
$scope module comparador $end
$var wire 1 5 comp_U $end
$var wire 1 6 comp_D $end
$var wire 4 : U [3:0] $end
$var wire 4 ; D [3:0] $end
$var reg 1 , x1 $end
$var reg 1 + x2 $end
$upscope $end
$scope module contador $end
$var wire 1 % clk $end
$var wire 6 < n [5:0] $end
$var wire 1 - resta $end
$var wire 1 3 ld $end
$var reg 6 = out_i [5:0] $end
$upscope $end
$scope module control_unit $end
$var wire 1 % clk $end
$var wire 1 & init $end
$var wire 1 ' rst_hardware $end
$var wire 1 , x1 $end
$var wire 1 + x2 $end
$var wire 1 * z $end
$var wire 1 4 error $end
$var parameter 4 > CHECK_1 $end
$var parameter 4 ? CHECK_D $end
$var parameter 4 @ CHECK_U $end
$var parameter 4 A DONE $end
$var parameter 4 B SH $end
$var parameter 4 C START $end
$var parameter 4 D SUM_D $end
$var parameter 4 E SUM_U $end
$var reg 1 6 comp_D $end
$var reg 1 5 comp_U $end
$var reg 1 " done $end
$var reg 1 3 ld $end
$var reg 1 2 new_D $end
$var reg 1 0 new_U $end
$var reg 1 - sh $end
$var reg 4 F state [3:0] $end
$upscope $end
$scope module reg_datos $end
$var wire 4 G A [3:0] $end
$var wire 4 H B [3:0] $end
$var wire 1 % clk $end
$var wire 1 3 ld $end
$var wire 1 2 new_D $end
$var wire 1 0 new_U $end
$var wire 1 - sh $end
$var wire 7 I num [6:0] $end
$var wire 4 J new_U_val [3:0] $end
$var wire 4 K new_D_val [3:0] $end
$var wire 4 L U [3:0] $end
$var wire 4 M D [3:0] $end
$var reg 15 N num_bcd [14:0] $end
$upscope $end
$scope module restador $end
$var wire 1 2 new_D $end
$var wire 1 0 new_U $end
$var wire 4 O out_D [3:0] $end
$var wire 4 P out_U [3:0] $end
$var reg 4 Q out_new_D [3:0] $end
$var reg 4 R out_new_U [3:0] $end
$upscope $end
$scope module validador $end
$var wire 4 S A [3:0] $end
$var wire 4 T B [3:0] $end
$var wire 1 4 Error $end
$var wire 1 U Error1 $end
$var wire 1 V Error2 $end
$upscope $end
$upscope $end
$upscope $end
$enddefinitions $end
$comment Show the parameter values. $end
$dumpall
b100 E
b110 D
b0 C
b1 B
b111 A
b11 @
b101 ?
b10 >
$end
#0
$dumpvars
0V
0U
b0 T
b0 S
bx R
bx Q
bx P
bx O
bx N
bx M
bx L
bx K
bx J
bx I
b0 H
b0 G
bx F
bx =
b111 <
bx ;
bx :
bx 9
bx 8
bx 7
x6
x5
04
x3
x2
bx 1
x0
bx /
bx .
x-
x,
x+
x*
b0 )
b0 (
1'
0&
0%
b0 $
b0 #
x"
bx !
$end
#5000
0+
0,
0"
02
00
06
05
0-
13
b0 F
1%
#10000
b0 1
b0 K
b0 Q
b0 /
b0 J
b0 R
b0 8
b0 ;
b0 M
b0 O
b0 7
b0 :
b0 L
b0 P
b0 !
b0 9
b0 I
0*
b111 .
b111 =
b0 N
0%
#15000
1%
#20000
0%
0'
#25000
1%
#30000
b100 1
b100 K
b100 Q
b101 /
b101 J
b101 R
b100 8
b100 ;
b100 M
b100 O
b101 7
b101 :
b101 L
b101 P
b10001010000000 N
0%
1&
b101 $
b101 )
b101 H
b101 T
b100 #
b100 (
b100 G
b100 S
#35000
1-
03
b1 F
1%
#40000
b10 1
b10 K
b10 Q
b10 /
b10 J
b10 R
b10 8
b10 ;
b10 M
b10 O
b10 7
b10 :
b10 L
b10 P
b1000000 !
b1000000 9
b1000000 I
b1000101000000 N
b110 .
b110 =
0%
#41000
0&
#45000
0-
b10 F
1%
#50000
0%
#55000
15
b11 F
1%
#60000
0%
#65000
16
05
b101 F
1%
#70000
0%
#75000
06
1-
b1 F
1%
#80000
b1 1
b1 K
b1 Q
b1 /
b1 J
b1 R
b1 8
b1 ;
b1 M
b1 O
b1 7
b1 :
b1 L
b1 P
b100000 !
b100000 9
b100000 I
b100010100000 N
b101 .
b101 =
0%
#85000
0-
b10 F
1%
#90000
0%
#95000
15
b11 F
1%
#100000
0%
#105000
16
05
b101 F
1%
#110000
0%
#115000
06
1-
b1 F
1%
#120000
b0 1
b0 K
b0 Q
b1000 /
b1000 J
b1000 R
b0 8
b0 ;
b0 M
b0 O
b1000 7
b1000 :
b1000 L
b1000 P
b1010000 !
b1010000 9
b1010000 I
b10001010000 N
b100 .
b100 =
0%
#125000
0-
b10 F
1%
#130000
0%
#135000
1,
15
b11 F
1%
#140000
0%
#145000
b101 /
b101 J
b101 R
0,
10
05
b100 F
1%
#150000
b10 /
b10 J
b10 R
b101 7
b101 :
b101 L
b101 P
b1011010000 N
0%
#155000
b101 /
b101 J
b101 R
00
16
b101 F
1%
#160000
0%
#165000
06
1-
b1 F
1%
#170000
b10 /
b10 J
b10 R
b10 7
b10 :
b10 L
b10 P
b1101000 !
b1101000 9
b1101000 I
b11 .
b11 =
b101101000 N
0%
#175000
0-
b10 F
1%
#180000
0%
#185000
15
b11 F
1%
#190000
0%
#195000
16
05
b101 F
1%
#200000
0%
#205000
06
1-
b1 F
1%
#210000
b1 /
b1 J
b1 R
b1 7
b1 :
b1 L
b1 P
b110100 !
b110100 9
b110100 I
b10 .
b10 =
b10110100 N
0%
#215000
0-
b10 F
1%
#220000
0%
#225000
15
b11 F
1%
#230000
0%
#235000
16
05
b101 F
1%
#240000
0%
#245000
06
1-
b1 F
1%
#250000
b0 /
b0 J
b0 R
b0 7
b0 :
b0 L
b0 P
b1011010 !
b1011010 9
b1011010 I
b1 .
b1 =
b1011010 N
0%
#255000
0-
b10 F
1%
#260000
0%
#265000
15
b11 F
1%
#270000
0%
#275000
16
05
b101 F
1%
#280000
0%
#285000
06
1-
b1 F
1%
#290000
b101101 !
b101101 9
b101101 I
1*
b0 .
b0 =
b101101 N
0%
#295000
0-
b10 F
1%
#300000
0%
#305000
1"
b111 F
1%
#310000
0%
#315000
0"
13
b0 F
1%
#320000
b100 1
b100 K
b100 Q
b101 /
b101 J
b101 R
b100 8
b100 ;
b100 M
b100 O
b101 7
b101 :
b101 L
b101 P
b0 !
b0 9
b0 I
b10001010000000 N
0*
b111 .
b111 =
0%
#325000
1%
#330000
0%
#335000
1%
#340000
0%
#345000
1%
#350000
0%
#355000
1%
#357000
1&
b1001 $
b1001 )
b1001 H
b1001 T
b1001 #
b1001 (
b1001 G
b1001 S
#360000
b1001 1
b1001 K
b1001 Q
b1001 /
b1001 J
b1001 R
b1001 8
b1001 ;
b1001 M
b1001 O
b1001 7
b1001 :
b1001 L
b1001 P
b100110010000000 N
0%
#365000
1-
03
b1 F
1%
#368000
0&
#370000
b100 1
b100 K
b100 Q
b1100 /
b1100 J
b1100 R
b100 8
b100 ;
b100 M
b100 O
b1100 7
b1100 :
b1100 L
b1100 P
b1000000 !
b1000000 9
b1000000 I
b110 .
b110 =
b10011001000000 N
0%
#375000
0-
b10 F
1%
#380000
0%
#385000
1,
15
b11 F
1%
#390000
0%
#395000
b1001 /
b1001 J
b1001 R
0,
10
05
b100 F
1%
#400000
b110 /
b110 J
b110 R
b1001 7
b1001 :
b1001 L
b1001 P
b10010011000000 N
0%
#405000
b1001 /
b1001 J
b1001 R
00
16
b101 F
1%
#410000
0%
#415000
06
1-
b1 F
1%
#420000
b10 1
b10 K
b10 Q
b100 /
b100 J
b100 R
b10 8
b10 ;
b10 M
b10 O
b100 7
b100 :
b100 L
b100 P
b1100000 !
b1100000 9
b1100000 I
b1001001100000 N
b101 .
b101 =
0%
#425000
0-
b10 F
1%
#430000
0%
#435000
15
b11 F
1%
#440000
0%
#445000
16
05
b101 F
1%
#450000
0%
#455000
06
1-
b1 F
1%
#460000
b1 1
b1 K
b1 Q
b10 /
b10 J
b10 R
b1 8
b1 ;
b1 M
b1 O
b10 7
b10 :
b10 L
b10 P
b110000 !
b110000 9
b110000 I
b100100110000 N
b100 .
b100 =
0%
#465000
0-
b10 F
1%
#470000
0%
#475000
15
b11 F
1%
#480000
0%
#485000
16
05
b101 F
1%
#490000
0%
#495000
06
1-
b1 F
1%
#500000
b0 1
b0 K
b0 Q
b1001 /
b1001 J
b1001 R
b0 8
b0 ;
b0 M
b0 O
b1001 7
b1001 :
b1001 L
b1001 P
b11000 !
b11000 9
b11000 I
b10010011000 N
b11 .
b11 =
0%
#505000
0-
b10 F
1%
#510000
0%
#515000
1,
15
b11 F
1%
#520000
0%
#525000
b110 /
b110 J
b110 R
0,
10
05
b100 F
1%
#530000
b11 /
b11 J
b11 R
b110 7
b110 :
b110 L
b110 P
b1100011000 N
0%
#535000
b110 /
b110 J
b110 R
00
16
b101 F
1%
#540000
0%
#545000
06
1-
b1 F
1%
#550000
b11 /
b11 J
b11 R
b11 7
b11 :
b11 L
b11 P
b1100 !
b1100 9
b1100 I
b10 .
b10 =
b110001100 N
0%
#555000
0-
b10 F
1%
#560000
0%
#565000
15
b11 F
1%
#570000
0%
#575000
16
05
b101 F
1%
#580000
0%
#585000
06
1-
b1 F
1%
#590000
b1 /
b1 J
b1 R
b1 7
b1 :
b1 L
b1 P
b1000110 !
b1000110 9
b1000110 I
b1 .
b1 =
b11000110 N
0%
#595000
0-
b10 F
1%
#600000
0%
#605000
15
b11 F
1%
#610000
0%
#615000
16
05
b101 F
1%
#620000
0%
#625000
06
1-
b1 F
1%
#630000
b0 /
b0 J
b0 R
b0 7
b0 :
b0 L
b0 P
b1100011 !
b1100011 9
b1100011 I
1*
b0 .
b0 =
b1100011 N
0%
#635000
0-
b10 F
1%
#640000
0%
#645000
1"
b111 F
1%
#650000
0%
#655000
0"
13
b0 F
1%
#660000
b1001 1
b1001 K
b1001 Q
b1001 /
b1001 J
b1001 R
b1001 8
b1001 ;
b1001 M
b1001 O
b1001 7
b1001 :
b1001 L
b1001 P
b0 !
b0 9
b0 I
b100110010000000 N
0*
b111 .
b111 =
0%
