Entregas finales/códigos/multiplicador/comp_mult.v
module comp_mult(
    input  [15:0] B,
    output X
);

assign X = (B == 16'd0);

endmodule

Entregas finales/códigos/multiplicador/acc.v
module acc(
    input clk,
    input reset,
    input add,
    input  [31:0] A,
    output reg [31:0] R
);

always @(negedge clk) begin
    if (reset)
        R <= 32'b0;
    else if (add)
        R <= R + A;
    else
        R <= R;
end

endmodule

Entregas finales/códigos/multiplicador/reg_B.v
module reg_B(
    input clk,
    input ld,
    input sh,
    input  [15:0] b,
    output reg [15:0] B_out,
    output LSB_B
);

assign LSB_B = B_out[0];

always @(negedge clk) begin
    if (ld)
        B_out <= b;
    else if (sh)
        B_out <= B_out >> 1;
    else
        B_out <= B_out;
end

endmodule

Entregas finales/códigos/multiplicador/reg_A.v
module reg_A(
    input clk,
    input ld,
    input sh,
    input  [15:0] a,
    output reg [31:0] A_out
);

always @(negedge clk) begin
    if (ld)
        A_out <= a;   
    else if (sh)
        A_out <= A_out << 1;   
    else
        A_out <= A_out;
end

endmodule

Entregas finales/códigos/multiplicador/control.v
module control (
    input clk,
    input rst_hardware,
    input init,
    input lsbb,
    input x,
    output reg sh,
    output reg reset,
    output reg add,
    output reg done
);

reg [2:0] state;
localparam START   = 3'b000,
           REVISAR = 3'b001,
           SUMADOR = 3'b010,
           CORRER  = 3'b011,
           COMPARA = 3'b100,
           HECHO   = 3'b101;

// 1. Bloque secuencial: Transicion de estados
always @(posedge clk) begin
    if (rst_hardware) begin
        state <= START;
    end else begin
        case(state)
            START: begin
                if (init)
                    state <= REVISAR;
                else
                    state <= START;
            end
            REVISAR: begin
                if (lsbb)
                    state <= SUMADOR;
                else
                    state <= CORRER;
            end
            SUMADOR: begin
                state <= CORRER;
            end
            CORRER: begin
                state <= COMPARA;
            end
            COMPARA: begin
                if (x)
                    state <= HECHO;
                else
                    state <= REVISAR;
            end
            HECHO: begin
                if (init)
                    state <= HECHO;
                else
                    state <= START;
            end
            default: state <= START;
        endcase
    end
end

// 2. Bloque combinacional: Salidas de control segun el estado
always @(*) begin
    case(state)
        START:   begin 
            sh=0; 
            reset=1; 
            add=0; 
            done=0; 
        end
        REVISAR: begin 
            sh=0; 
            reset=0; 
            add=0; 
            done=0; 
        end
        SUMADOR: begin 
            sh=0; 
            reset=0; 
            add=1; 
            done=0; 
        end
        CORRER:  begin 
            sh=1; 
            reset=0; 
            add=0; 
            done=0; 
        end
        COMPARA: begin 
            sh=0; 
            reset=0; 
            add=0; 
            done=0; 
        end
        HECHO:   begin 
            sh=0; 
            reset=0; 
            add=0; 
            done=1; 
        end
        default: begin 
            sh=0; 
            reset=0; 
            add=0; 
            done=0; 
        end
    endcase
end

endmodule

Entregas finales/códigos/multiplicador/multiplicador.v
module multiplicador(
    input clk,
    input rst_hardware,
    input init,
    input  [15:0] multiplicando,
    input  [15:0] multiplicador,
    output [31:0] R,
    output done
);

// 1. CABLES INTERNOS DE CONTROL
wire w_sh;
wire w_reset;
wire w_add;
wire w_lsbb;
wire w_x;

// 2. CABLES INTERNOS DE DATOS
wire [31:0] w_A;
wire [15:0] w_B;

// 3. CONEXION DE MODULOS
control control_unit (
    .clk(clk),
    .rst_hardware(rst_hardware),
    .init(init),
    .lsbb(w_lsbb),
    .x(w_x),
    .sh(w_sh),
    .reset(w_reset),
    .add(w_add),
    .done(done)
);

reg_A reg_multiplicando (
    .clk(clk),
    .ld(w_reset),
    .sh(w_sh),
    .a(multiplicando),
    .A_out(w_A)
);

reg_B reg_multiplicador (
    .clk(clk),
    .ld(w_reset),
    .sh(w_sh),
    .b(multiplicador),
    .B_out(w_B),
    .LSB_B(w_lsbb)
);

acc acumulador (
    .clk(clk),
    .reset(w_reset),
    .add(w_add),
    .A(w_A),
    .R(R)
);

comp_mult comparador (
    .B(w_B),
    .X(w_x)
);

endmodule

Entregas finales/códigos/multiplicador/multiplicador_TB.v
`timescale 1ns/1ps

module multiplicador_TB;
reg clk;
reg rst_hardware;
reg init;
reg [15:0] multiplicando;
reg [15:0] multiplicador;
wire [31:0] R;
wire done;

multiplicador uut (
        .clk(clk),
        .rst_hardware(rst_hardware),
        .init(init),
        .multiplicando(multiplicando),
        .multiplicador(multiplicador),
        .R(R),
        .done(done)
    );

always #5 clk = ~clk;

initial begin
$dumpfile("multiplicador_TB.vcd");
$dumpvars(0, multiplicador_TB);

//estado Inicial
        clk = 0;
        rst_hardware = 1;
        init = 0;
        multiplicando = 16'd0;
        multiplicador = 16'd0;
#20;

        rst_hardware = 0;
#10;

// PRUEBA 1: 5 x 6 = 30
        multiplicando = 16'd5;
        multiplicador = 16'd6;
        init = 1;
#11;
        init = 0;

        @(posedge done);
#11;
$display("PRUEBA 1 -> %d x %d = %d", multiplicando, multiplicador, R);
#41;

// PRUEBA 2: 12 x 11 = 132
        multiplicando = 16'd12;
        multiplicador = 16'd11;
        init = 1;
#11;
        init = 0;

        @(posedge done);
#11;
$display("PRUEBA 2 -> %d x %d = %d", multiplicando, multiplicador, R);
#41;

$finish;
end

endmodule

Entregas finales/códigos/multiplicador/multiplicador_TB.vcd
$date
	Mon Jul 13 22:11:55 2026
$end
$version
	Icarus Verilog
$end
$timescale
	1ps
$end
$scope module multiplicador_TB $end
$var wire 1 ! done $end
$var wire 32 " R [31:0] $end
$var reg 1 # clk $end
$var reg 1 $ init $end
$var reg 16 % multiplicador [15:0] $end
$var reg 16 & multiplicando [15:0] $end
$var reg 1 ' rst_hardware $end
$scope module uut $end
$var wire 1 # clk $end
$var wire 1 $ init $end
$var wire 16 ( multiplicador [15:0] $end
$var wire 16 ) multiplicando [15:0] $end
$var wire 1 ' rst_hardware $end
$var wire 1 * w_x $end
$var wire 1 + w_sh $end
$var wire 1 , w_reset $end
$var wire 1 - w_lsbb $end
$var wire 1 . w_add $end
$var wire 16 / w_B [15:0] $end
$var wire 32 0 w_A [31:0] $end
$var wire 1 ! done $end
$var wire 32 1 R [31:0] $end
$scope module acumulador $end
$var wire 1 # clk $end
$var wire 1 , reset $end
$var wire 1 . add $end
$var wire 32 2 A [31:0] $end
$var reg 32 3 R [31:0] $end
$upscope $end
$scope module comparador $end
$var wire 1 * X $end
$var wire 16 4 B [15:0] $end
$upscope $end
$scope module control_unit $end
$var wire 1 # clk $end
$var wire 1 $ init $end
$var wire 1 ' rst_hardware $end
$var wire 1 * x $end
$var wire 1 - lsbb $end
$var parameter 3 5 COMPARA $end
$var parameter 3 6 CORRER $end
$var parameter 3 7 HECHO $end
$var parameter 3 8 REVISAR $end
$var parameter 3 9 START $end
$var parameter 3 : SUMADOR $end
$var reg 1 . add $end
$var reg 1 ! done $end
$var reg 1 , reset $end
$var reg 1 + sh $end
$var reg 3 ; state [2:0] $end
$upscope $end
$scope module reg_multiplicador $end
$var wire 16 < b [15:0] $end
$var wire 1 # clk $end
$var wire 1 , ld $end
$var wire 1 + sh $end
$var wire 1 - LSB_B $end
$var reg 16 = B_out [15:0] $end
$upscope $end
$scope module reg_multiplicando $end
$var wire 16 > a [15:0] $end
$var wire 1 # clk $end
$var wire 1 , ld $end
$var wire 1 + sh $end
$var reg 32 ? A_out [31:0] $end
$upscope $end
$upscope $end
$upscope $end
$enddefinitions $end
$comment Show the parameter values. $end
$dumpall
b10 :
b0 9
b1 8
b101 7
b11 6
b100 5
$end
#0
$dumpvars
bx ?
b0 >
bx =
b0 <
bx ;
bx 4
bx 3
bx 2
bx 1
bx 0
bx /
x.
x-
x,
x+
x*
b0 )
b0 (
1'
b0 &
b0 %
0$
0#
bx "
x!
$end
#5000
0!
0.
1,
0+
b0 ;
1#
#10000
0-
b0 "
b0 1
b0 3
1*
b0 /
b0 4
b0 =
b0 0
b0 2
b0 ?
0#
#15000
1#
#20000
0#
0'
#25000
1#
#30000
0*
b110 /
b110 4
b110 =
b101 0
b101 2
b101 ?
0#
1$
b110 %
b110 (
b110 <
b101 &
b101 )
b101 >
#35000
0,
b1 ;
1#
#40000
0#
#41000
0$
#45000
1+
b11 ;
1#
#50000
1-
b11 /
b11 4
b11 =
b1010 0
b1010 2
b1010 ?
0#
#55000
0+
b100 ;
1#
#60000
0#
#65000
b1 ;
1#
#70000
0#
#75000
1.
b10 ;
1#
#80000
b1010 "
b1010 1
b1010 3
0#
#85000
0.
1+
b11 ;
1#
#90000
b1 /
b1 4
b1 =
b10100 0
b10100 2
b10100 ?
0#
#95000
0+
b100 ;
1#
#100000
0#
#105000
b1 ;
1#
#110000
0#
#115000
1.
b10 ;
1#
#120000
b11110 "
b11110 1
b11110 3
0#
#125000
0.
1+
b11 ;
1#
#130000
0-
1*
b0 /
b0 4
b0 =
b101000 0
b101000 2
b101000 ?
0#
#135000
0+
b100 ;
1#
#140000
0#
#145000
1!
b101 ;
1#
#150000
0#
#155000
0!
1,
b0 ;
1#
#160000
b101 0
b101 2
b101 ?
0*
b110 /
b110 4
b110 =
b0 "
b0 1
b0 3
0#
#165000
1#
#170000
0#
#175000
1#
#180000
0#
#185000
1#
#190000
0#
#195000
1#
#197000
1$
b1011 %
b1011 (
b1011 <
b1100 &
b1100 )
b1100 >
#200000
1-
b1100 0
b1100 2
b1100 ?
b1011 /
b1011 4
b1011 =
0#
#205000
0,
b1 ;
1#
#208000
0$
#210000
0#
#215000
1.
b10 ;
1#
#220000
b1100 "
b1100 1
b1100 3
0#
#225000
0.
1+
b11 ;
1#
#230000
b101 /
b101 4
b101 =
b11000 0
b11000 2
b11000 ?
0#
#235000
0+
b100 ;
1#
#240000
0#
#245000
b1 ;
1#
#250000
0#
#255000
1.
b10 ;
1#
#260000
b100100 "
b100100 1
b100100 3
0#
#265000
0.
1+
b11 ;
1#
#270000
0-
b10 /
b10 4
b10 =
b110000 0
b110000 2
b110000 ?
0#
#275000
0+
b100 ;
1#
#280000
0#
#285000
b1 ;
1#
#290000
0#
#295000
1+
b11 ;
1#
#300000
1-
b1100000 0
b1100000 2
b1100000 ?
b1 /
b1 4
b1 =
0#
#305000
0+
b100 ;
1#
#310000
0#
#315000
b1 ;
1#
#320000
0#
#325000
1.
b10 ;
1#
#330000
b10000100 "
b10000100 1
b10000100 3
0#
#335000
0.
1+
b11 ;
1#
#340000
0-
b11000000 0
b11000000 2
b11000000 ?
1*
b0 /
b0 4
b0 =
0#
#345000
0+
b100 ;
1#
#350000
0#
#355000
1!
b101 ;
1#
#360000
0#
#365000
0!
1,
b0 ;
1#
#370000
1-
b0 "
b0 1
b0 3
0*
b1011 /
b1011 4
b1011 =
b1100 0
b1100 2
b1100 ?
0#
