Entregas finales/códigos/Divisor/count.v
module count (
    input clk,
    input ld,
    input resta,
    input [5:0] n,                 
    output reg [5:0] out_count);   
    always @(negedge clk) begin
        if (ld)
            out_count <= n;                  
        else if (resta)
            out_count <= out_count - 1;      
        else
            out_count <= out_count;          
    end
endmodule

Entregas finales/códigos/Divisor/resp.v
module resp (
    input clk,
    input rst,
    input sh_2,
    input r0, 
    output reg [31:0] resp_out                        
);

    always @(negedge clk) begin
        if (rst) begin                 
            resp_out <= 32'd0;         
        end
        else if (sh_2) begin
            resp_out <= {resp_out[30:0], r0};
        end
        else begin
            resp_out <= resp_out;   
        end
    end

endmodule

Entregas finales/códigos/Divisor/sumadorC2.v
module sumadorC2 (
    input [31:0] resi_in,
    input [31:0] b_in,
    output [31:0] new_resi,
    output comp
);

assign new_resi = resi_in - b_in;
assign comp = new_resi[31];

endmodule

Entregas finales/códigos/Divisor/num_divisor.v
module num_divisor (
    input [31:0] b,
    input ld,
    input clk,
    output reg [31:0] num_divisor_out);

    always @(negedge clk) begin
        if (ld)
            num_divisor_out <= b;
        else
            num_divisor_out <= num_divisor_out;
    end
endmodule

Entregas finales/códigos/Divisor/num_divid.v
module num_divid(
    input clk,
    input rst,
    input sh_1,
    input add_new_Resi,
    input [31:0] divid,
    input [31:0] new_resi,
    output [31:0] resi_out,
    output [31:0] sub_a_out);
    reg [63:0] registro_completo;
    
    assign resi_out  = registro_completo[63:32]; 
    assign sub_a_out = registro_completo[31:0];

    always @(negedge clk) begin
       if (rst)begin
            registro_completo <= {32'd0, divid};
        end
        else if  (sh_1)begin
            registro_completo <= {registro_completo[62:0], 1'b0};
        end
        else if (add_new_Resi)begin
            registro_completo <= {new_resi, registro_completo[31:0]};
        end
        else begin
            registro_completo <= registro_completo; // Mantiene el valor
        end
    end
endmodule

Entregas finales/códigos/Divisor/control.v
module control (
    input clk,
    input rst_hardware, 
    input init,
    input comp,
    input x,
    output reg rst,
    output reg sh_1,
    output reg sh_2,
    output reg new_Resi,
    output reg done
);

    // Definición de los estados
    reg [2:0] state, next_state;

    localparam START   = 3'b000,
               SHIFT_A = 3'b001,
               CHECK_1 = 3'b010,
               RESP_1  = 3'b011,
               RESP_0  = 3'b100,
               CHECK_2 = 3'b101,
               DONE    = 3'b110;

// 2. Bloque secuencial: Transición de estados
always @(posedge clk) begin
    if (rst_hardware) begin
        state <= START;
    end else begin
    case(state)

    START: begin
        if(init)
            state <= SHIFT_A;
        else
            state <= START;
    end

    SHIFT_A: begin
        state <= CHECK_1;
    end

    CHECK_1: begin
        if (comp)
            state<= RESP_0;
        else
            state <=RESP_1;
    end

    RESP_0: begin
        state<=CHECK_2;
    end

    RESP_1: begin
        state<=CHECK_2;
    end

    CHECK_2: begin
        if (x)
            state<=DONE;
        else
            state<=SHIFT_A;
    end

    DONE: begin
        state<=START;
    end
endcase
end
end

    always @(state) 
    begin
        case(state)

    START: begin
        rst = 1;
        sh_1 = 0;
        sh_2 = 0;
        new_Resi = 0;
        done = 0;
    end

    SHIFT_A: begin
        rst = 0;
        sh_1 = 1;
        sh_2 = 0;
        new_Resi = 0;
        done = 0;
    end

    CHECK_1: begin
        rst = 0;
        sh_1 = 0;
        sh_2 = 0;
        new_Resi = 0;
        done = 0;
    end

    RESP_0: begin
        rst = 0;
        sh_1 = 0;
        sh_2 = 1;
        new_Resi = 0;
        done = 0;
    end

    RESP_1: begin
        rst = 0;
        sh_1 = 0;
        sh_2 = 1;
        new_Resi = 1;
        done = 0;
    end

    CHECK_2: begin
        rst = 0;
        sh_1 = 0;
        sh_2 = 0;
        new_Resi = 0;
        done = 0;
    end

    DONE: begin
        rst = 0;
        sh_1 = 0;
        sh_2 = 0;
        new_Resi = 0;
        done = 1;
    end

    endcase
end
endmodule

Entregas finales/códigos/Divisor/divisor.v
module divisor(
    input clk,
    input rst_hardware,   
    input init,           
    input [31:0] divida,  
    input [31:0] divisb,  
    output [31:0] res_div,
    output [31:0] resi,   
    output done_div      
);

    
    // CABLES INTERNOS DE CONTROL 
  
    wire w_rst;
    wire w_sh_1;
    wire w_sh_2;
    wire w_new_Resi;
    wire w_comp;
    wire w_x;

  
    // 2. CABLES INTERNOS DE DATOS
   
    wire [31:0] w_resi_out;      
    wire [31:0] w_sub_a_out;     
    wire [31:0] w_num_divisor_out;
    wire [31:0] w_new_resi_bus;   
    wire [5:0]  w_out_count;     

 // 3. LÓGICA DE ACOPLAMIENTO 

    assign w_x = (w_out_count == 4'd0);

 
    assign resi = w_resi_out;


    
    // 4. CONEXIÓN DE MÓDULOS
  

    control control_unit (
        .clk(clk),
        .rst_hardware(rst_hardware),
        .init(init),
        .comp(w_comp),
        .x(w_x),
        .rst(w_rst),
        .sh_1(w_sh_1),
        .sh_2(w_sh_2),
        .new_Resi(w_new_Resi),
        .done(done_div)
    );

    num_divid dividendo (
        .clk(clk),
        .rst(w_rst),
        .sh_1(w_sh_1),
        .add_new_Resi(w_new_Resi),
        .divid(divida),
        .new_resi(w_new_resi_bus),
        .resi_out(w_resi_out),
        .sub_a_out(w_sub_a_out)
    );


    num_divisor divisor (
        .clk(clk),
        .ld(w_rst),
        .b(divisb),
        .num_divisor_out(w_num_divisor_out)
    );


    sumadorC2 restador (
        .resi_in(w_resi_out),
        .b_in(w_num_divisor_out),
        .new_resi(w_new_resi_bus),
        .comp(w_comp)
    );

    
    resp respuesta (
        .clk(clk),
        .rst(w_rst),
        .sh_2(w_sh_2),
        .r0(w_new_Resi), 
        .resp_out(res_div)
    );


    count contador (
        .clk(clk),
        .ld(w_rst),
        .resta(w_sh_1),
        .n(6'd32),
        .out_count(w_out_count)
    );

endmodule

Entregas finales/códigos/Divisor/divisor_TB.v
`timescale 1ns/1ps

module divisor_TB; 
   
    reg clk;
    reg rst_hardware;
    reg init;
    reg [31:0] divida;
    reg [31:0] divisb;
    
    wire [31:0] res_div;
    wire [31:0] resi;
    wire done_div;

    
    divisor uut (
        .clk(clk),
        .rst_hardware(rst_hardware),
        .init(init),
        .divida(divida),
        .divisb(divisb),
        .res_div(res_div),
        .resi(resi),
        .done_div(done_div)
    );

   
    always #5 clk = ~clk;

    
    initial begin
        
        $dumpfile("divisor_TB.vcd");
        $dumpvars(0, divisor_TB);

        //estado Inicial
        clk = 0;
        rst_hardware = 1; 
        init = 0;
        divida = 32'd0;
        divisb = 32'd0;
        #20;              

        rst_hardware = 0; 
        #10;

        // PRUEBA 1: 20 dividido entre 4
    
        divida = 32'd20;  
        divisb = 32'd4;   
        init = 1;         
        #11;
        init = 0;        

       
        @(posedge done_div);
        #11;
        $display("PRUEBA 1 -> %d / %d = Cociente: %d, Residuo: %d", divida, divisb, res_div, resi);
        #41;

        // PRUEBA 2: 45 dividido entre 6
        divida = 32'd45;  
        divisb = 32'd6;   
        init = 1;         
#11;
        init = 0;         

        @(posedge done_div);
#11;
$display("PRUEBA 2 -> %d / %d = Cociente: %d, Residuo: %d", divida, divisb, res_div, resi);
#41;


        
        $finish;
    end

endmodule

Entregas finales/códigos/Divisor/divisor_TB.vcd
$date
	Mon Jul 13 15:28:00 2026
$end
$version
	Icarus Verilog
$end
$timescale
	1ps
$end
$scope module divisor_TB $end
$var wire 32 ! resi [31:0] $end
$var wire 32 " res_div [31:0] $end
$var wire 1 # done_div $end
$var reg 1 $ clk $end
$var reg 32 % divida [31:0] $end
$var reg 32 & divisb [31:0] $end
$var reg 1 ' init $end
$var reg 1 ( rst_hardware $end
$scope module uut $end
$var wire 1 $ clk $end
$var wire 32 ) divida [31:0] $end
$var wire 32 * divisb [31:0] $end
$var wire 1 ' init $end
$var wire 32 + resi [31:0] $end
$var wire 1 ( rst_hardware $end
$var wire 1 , w_x $end
$var wire 32 - w_sub_a_out [31:0] $end
$var wire 1 . w_sh_2 $end
$var wire 1 / w_sh_1 $end
$var wire 1 0 w_rst $end
$var wire 32 1 w_resi_out [31:0] $end
$var wire 6 2 w_out_count [5:0] $end
$var wire 32 3 w_num_divisor_out [31:0] $end
$var wire 32 4 w_new_resi_bus [31:0] $end
$var wire 1 5 w_new_Resi $end
$var wire 1 6 w_comp $end
$var wire 32 7 res_div [31:0] $end
$var wire 1 # done_div $end
$scope module contador $end
$var wire 1 $ clk $end
$var wire 6 8 n [5:0] $end
$var wire 1 / resta $end
$var wire 1 0 ld $end
$var reg 6 9 out_count [5:0] $end
$upscope $end
$scope module control_unit $end
$var wire 1 $ clk $end
$var wire 1 ' init $end
$var wire 1 ( rst_hardware $end
$var wire 1 , x $end
$var wire 1 6 comp $end
$var parameter 3 : CHECK_1 $end
$var parameter 3 ; CHECK_2 $end
$var parameter 3 < DONE $end
$var parameter 3 = RESP_0 $end
$var parameter 3 > RESP_1 $end
$var parameter 3 ? SHIFT_A $end
$var parameter 3 @ START $end
$var reg 1 # done $end
$var reg 1 5 new_Resi $end
$var reg 1 0 rst $end
$var reg 1 / sh_1 $end
$var reg 1 . sh_2 $end
$var reg 3 A state [2:0] $end
$upscope $end
$scope module dividendo $end
$var wire 1 5 add_new_Resi $end
$var wire 1 $ clk $end
$var wire 32 B divid [31:0] $end
$var wire 1 0 rst $end
$var wire 1 / sh_1 $end
$var wire 32 C sub_a_out [31:0] $end
$var wire 32 D resi_out [31:0] $end
$var wire 32 E new_resi [31:0] $end
$var reg 64 F registro_completo [63:0] $end
$upscope $end
$scope module divisor $end
$var wire 32 G b [31:0] $end
$var wire 1 $ clk $end
$var wire 1 0 ld $end
$var reg 32 H num_divisor_out [31:0] $end
$upscope $end
$scope module respuesta $end
$var wire 1 $ clk $end
$var wire 1 5 r0 $end
$var wire 1 0 rst $end
$var wire 1 . sh_2 $end
$var reg 32 I resp_out [31:0] $end
$upscope $end
$scope module restador $end
$var wire 32 J b_in [31:0] $end
$var wire 32 K resi_in [31:0] $end
$var wire 32 L new_resi [31:0] $end
$var wire 1 6 comp $end
$upscope $end
$upscope $end
$upscope $end
$enddefinitions $end
$comment Show the parameter values. $end
$dumpall
b0 @
b1 ?
b11 >
b100 =
b110 <
b101 ;
b10 :
$end
#0
$dumpvars
bx L
bx K
bx J
bx I
bx H
b0 G
bx F
bx E
bx D
bx C
b0 B
bx A
bx 9
b100000 8
bx 7
x6
x5
bx 4
bx 3
bx 2
bx 1
x0
x/
x.
bx -
x,
bx +
b0 *
b0 )
1(
0'
b0 &
b0 %
0$
x#
bx "
bx !
$end
#5000
0#
05
0.
0/
10
b0 A
1$
#10000
06
b0 4
b0 E
b0 L
b0 !
b0 +
b0 1
b0 D
b0 K
b0 -
b0 C
0,
b100000 2
b100000 9
b0 "
b0 7
b0 I
b0 3
b0 H
b0 J
b0 F
0$
#15000
1$
#20000
0$
0(
#25000
1$
#30000
16
b10100 -
b10100 C
b11111111111111111111111111111100 4
b11111111111111111111111111111100 E
b11111111111111111111111111111100 L
b100 3
b100 H
b100 J
b10100 F
0$
1'
b100 &
b100 *
b100 G
b10100 %
b10100 )
b10100 B
#35000
1/
00
b1 A
1$
#40000
b101000 -
b101000 C
b101000 F
b11111 2
b11111 9
0$
#41000
0'
#45000
0/
b10 A
1$
#50000
0$
#55000
1.
b100 A
1$
#60000
0$
#65000
0.
b101 A
1$
#70000
0$
#75000
1/
b1 A
1$
#80000
b1010000 -
b1010000 C
b1010000 F
b11110 2
b11110 9
0$
#85000
0/
b10 A
1$
#90000
0$
#95000
1.
b100 A
1$
#100000
0$
#105000
0.
b101 A
1$
#110000
0$
#115000
1/
b1 A
1$
#120000
b10100000 -
b10100000 C
b10100000 F
b11101 2
b11101 9
0$
#125000
0/
b10 A
1$
#130000
0$
#135000
1.
b100 A
1$
#140000
0$
#145000
0.
b101 A
1$
#150000
0$
#155000
1/
b1 A
1$
#160000
b101000000 -
b101000000 C
b101000000 F
b11100 2
b11100 9
0$
#165000
0/
b10 A
1$
#170000
0$
#175000
1.
b100 A
1$
#180000
0$
#185000
0.
b101 A
1$
#190000
0$
#195000
1/
b1 A
1$
#200000
b1010000000 -
b1010000000 C
b1010000000 F
b11011 2
b11011 9
0$
#205000
0/
b10 A
1$
#210000
0$
#215000
1.
b100 A
1$
#220000
0$
#225000
0.
b101 A
1$
#230000
0$
#235000
1/
b1 A
1$
#240000
b10100000000 -
b10100000000 C
b10100000000 F
b11010 2
b11010 9
0$
#245000
0/
b10 A
1$
#250000
0$
#255000
1.
b100 A
1$
#260000
0$
#265000
0.
b101 A
1$
#270000
0$
#275000
1/
b1 A
1$
#280000
b101000000000 -
b101000000000 C
b101000000000 F
b11001 2
b11001 9
0$
#285000
0/
b10 A
1$
#290000
0$
#295000
1.
b100 A
1$
#300000
0$
#305000
0.
b101 A
1$
#310000
0$
#315000
1/
b1 A
1$
#320000
b1010000000000 -
b1010000000000 C
b1010000000000 F
b11000 2
b11000 9
0$
#325000
0/
b10 A
1$
#330000
0$
#335000
1.
b100 A
1$
#340000
0$
#345000
0.
b101 A
1$
#350000
0$
#355000
1/
b1 A
1$
#360000
b10100000000000 -
b10100000000000 C
b10100000000000 F
b10111 2
b10111 9
0$
#365000
0/
b10 A
1$
#370000
0$
#375000
1.
b100 A
1$
#380000
0$
#385000
0.
b101 A
1$
#390000
0$
#395000
1/
b1 A
1$
#400000
b101000000000000 -
b101000000000000 C
b101000000000000 F
b10110 2
b10110 9
0$
#405000
0/
b10 A
1$
#410000
0$
#415000
1.
b100 A
1$
#420000
0$
#425000
0.
b101 A
1$
#430000
0$
#435000
1/
b1 A
1$
#440000
b1010000000000000 -
b1010000000000000 C
b1010000000000000 F
b10101 2
b10101 9
0$
#445000
0/
b10 A
1$
#450000
0$
#455000
1.
b100 A
1$
#460000
0$
#465000
0.
b101 A
1$
#470000
0$
#475000
1/
b1 A
1$
#480000
b10100000000000000 -
b10100000000000000 C
b10100000000000000 F
b10100 2
b10100 9
0$
#485000
0/
b10 A
1$
#490000
0$
#495000
1.
b100 A
1$
#500000
0$
#505000
0.
b101 A
1$
#510000
0$
#515000
1/
b1 A
1$
#520000
b101000000000000000 -
b101000000000000000 C
b101000000000000000 F
b10011 2
b10011 9
0$
#525000
0/
b10 A
1$
#530000
0$
#535000
1.
b100 A
1$
#540000
0$
#545000
0.
b101 A
1$
#550000
0$
#555000
1/
b1 A
1$
#560000
b1010000000000000000 -
b1010000000000000000 C
b1010000000000000000 F
b10010 2
b10010 9
0$
#565000
0/
b10 A
1$
#570000
0$
#575000
1.
b100 A
1$
#580000
0$
#585000
0.
b101 A
1$
#590000
0$
#595000
1/
b1 A
1$
#600000
b10100000000000000000 -
b10100000000000000000 C
b10100000000000000000 F
b10001 2
b10001 9
0$
#605000
0/
b10 A
1$
#610000
0$
#615000
1.
b100 A
1$
#620000
0$
#625000
0.
b101 A
1$
#630000
0$
#635000
1/
b1 A
1$
#640000
b101000000000000000000 -
b101000000000000000000 C
b101000000000000000000 F
b10000 2
b10000 9
0$
#645000
0/
b10 A
1$
#650000
0$
#655000
1.
b100 A
1$
#660000
0$
#665000
0.
b101 A
1$
#670000
0$
#675000
1/
b1 A
1$
#680000
b1010000000000000000000 -
b1010000000000000000000 C
b1010000000000000000000 F
b1111 2
b1111 9
0$
#685000
0/
b10 A
1$
#690000
0$
#695000
1.
b100 A
1$
#700000
0$
#705000
0.
b101 A
1$
#710000
0$
#715000
1/
b1 A
1$
#720000
b10100000000000000000000 -
b10100000000000000000000 C
b10100000000000000000000 F
b1110 2
b1110 9
0$
#725000
0/
b10 A
1$
#730000
0$
#735000
1.
b100 A
1$
#740000
0$
#745000
0.
b101 A
1$
#750000
0$
#755000
1/
b1 A
1$
#760000
b101000000000000000000000 -
b101000000000000000000000 C
b101000000000000000000000 F
b1101 2
b1101 9
0$
#765000
0/
b10 A
1$
#770000
0$
#775000
1.
b100 A
1$
#780000
0$
#785000
0.
b101 A
1$
#790000
0$
#795000
1/
b1 A
1$
#800000
b1010000000000000000000000 -
b1010000000000000000000000 C
b1010000000000000000000000 F
b1100 2
b1100 9
0$
#805000
0/
b10 A
1$
#810000
0$
#815000
1.
b100 A
1$
#820000
0$
#825000
0.
b101 A
1$
#830000
0$
#835000
1/
b1 A
1$
#840000
b10100000000000000000000000 -
b10100000000000000000000000 C
b10100000000000000000000000 F
b1011 2
b1011 9
0$
#845000
0/
b10 A
1$
#850000
0$
#855000
1.
b100 A
1$
#860000
0$
#865000
0.
b101 A
1$
#870000
0$
#875000
1/
b1 A
1$
#880000
b101000000000000000000000000 -
b101000000000000000000000000 C
b101000000000000000000000000 F
b1010 2
b1010 9
0$
#885000
0/
b10 A
1$
#890000
0$
#895000
1.
b100 A
1$
#900000
0$
#905000
0.
b101 A
1$
#910000
0$
#915000
1/
b1 A
1$
#920000
b1010000000000000000000000000 -
b1010000000000000000000000000 C
b1010000000000000000000000000 F
b1001 2
b1001 9
0$
#925000
0/
b10 A
1$
#930000
0$
#935000
1.
b100 A
1$
#940000
0$
#945000
0.
b101 A
1$
#950000
0$
#955000
1/
b1 A
1$
#960000
b10100000000000000000000000000 -
b10100000000000000000000000000 C
b10100000000000000000000000000 F
b1000 2
b1000 9
0$
#965000
0/
b10 A
1$
#970000
0$
#975000
1.
b100 A
1$
#980000
0$
#985000
0.
b101 A
1$
#990000
0$
#995000
1/
b1 A
1$
#1000000
b101000000000000000000000000000 -
b101000000000000000000000000000 C
b101000000000000000000000000000 F
b111 2
b111 9
0$
#1005000
0/
b10 A
1$
#1010000
0$
#1015000
1.
b100 A
1$
#1020000
0$
#1025000
0.
b101 A
1$
#1030000
0$
#1035000
1/
b1 A
1$
#1040000
b1010000000000000000000000000000 -
b1010000000000000000000000000000 C
b1010000000000000000000000000000 F
b110 2
b110 9
0$
#1045000
0/
b10 A
1$
#1050000
0$
#1055000
1.
b100 A
1$
#1060000
0$
#1065000
0.
b101 A
1$
#1070000
0$
#1075000
1/
b1 A
1$
#1080000
b10100000000000000000000000000000 -
b10100000000000000000000000000000 C
b10100000000000000000000000000000 F
b101 2
b101 9
0$
#1085000
0/
b10 A
1$
#1090000
0$
#1095000
1.
b100 A
1$
#1100000
0$
#1105000
0.
b101 A
1$
#1110000
0$
#1115000
1/
b1 A
1$
#1120000
b11111111111111111111111111111101 4
b11111111111111111111111111111101 E
b11111111111111111111111111111101 L
b1 !
b1 +
b1 1
b1 D
b1 K
b1000000000000000000000000000000 -
b1000000000000000000000000000000 C
b101000000000000000000000000000000 F
b100 2
b100 9
0$
#1125000
0/
b10 A
1$
#1130000
0$
#1135000
1.
b100 A
1$
#1140000
0$
#1145000
0.
b101 A
1$
#1150000
0$
#1155000
1/
b1 A
1$
#1160000
b11111111111111111111111111111110 4
b11111111111111111111111111111110 E
b11111111111111111111111111111110 L
b10 !
b10 +
b10 1
b10 D
b10 K
b10000000000000000000000000000000 -
b10000000000000000000000000000000 C
b1010000000000000000000000000000000 F
b11 2
b11 9
0$
#1165000
0/
b10 A
1$
#1170000
0$
#1175000
1.
b100 A
1$
#1180000
0$
#1185000
0.
b101 A
1$
#1190000
0$
#1195000
1/
b1 A
1$
#1200000
06
b1 4
b1 E
b1 L
b101 !
b101 +
b101 1
b101 D
b101 K
b0 -
b0 C
b10100000000000000000000000000000000 F
b10 2
b10 9
0$
#1205000
0/
b10 A
1$
#1210000
0$
#1215000
15
1.
b11 A
1$
#1220000
16
b11111111111111111111111111111101 4
b11111111111111111111111111111101 E
b11111111111111111111111111111101 L
b1 !
b1 +
b1 1
b1 D
b1 K
b100000000000000000000000000000000 F
b1 "
b1 7
b1 I
0$
#1225000
05
0.
b101 A
1$
#1230000
0$
#1235000
1/
b1 A
1$
#1240000
b11111111111111111111111111111110 4
b11111111111111111111111111111110 E
b11111111111111111111111111111110 L
b10 !
b10 +
b10 1
b10 D
b10 K
b1000000000000000000000000000000000 F
b1 2
b1 9
0$
#1245000
0/
b10 A
1$
#1250000
0$
#1255000
1.
b100 A
1$
#1260000
b10 "
b10 7
b10 I
0$
#1265000
0.
b101 A
1$
#1270000
0$
#1275000
1/
b1 A
1$
#1280000
06
b0 4
b0 E
b0 L
b100 !
b100 +
b100 1
b100 D
b100 K
b10000000000000000000000000000000000 F
1,
b0 2
b0 9
0$
#1285000
0/
b10 A
1$
#1290000
0$
#1295000
15
1.
b11 A
1$
#1300000
16
b11111111111111111111111111111100 4
b11111111111111111111111111111100 E
b11111111111111111111111111111100 L
b0 !
b0 +
b0 1
b0 D
b0 K
b0 F
b101 "
b101 7
b101 I
0$
#1305000
05
0.
b101 A
1$
#1310000
0$
#1315000
1#
b110 A
1$
#1320000
0$
#1325000
0#
10
b0 A
1$
#1330000
b10100 -
b10100 C
0,
b100000 2
b100000 9
b0 "
b0 7
b0 I
b10100 F
0$
#1335000
1$
#1340000
0$
#1345000
1$
#1350000
0$
#1355000
1$
#1360000
0$
#1365000
1$
#1367000
1'
b110 &
b110 *
b110 G
b101101 %
b101101 )
b101101 B
#1370000
b101101 -
b101101 C
b11111111111111111111111111111010 4
b11111111111111111111111111111010 E
b11111111111111111111111111111010 L
b110 3
b110 H
b110 J
b101101 F
0$
#1375000
1/
00
b1 A
1$
#1378000
0'
#1380000
b1011010 -
b1011010 C
b1011010 F
b11111 2
b11111 9
0$
#1385000
0/
b10 A
1$
#1390000
0$
#1395000
1.
b100 A
1$
#1400000
0$
#1405000
0.
b101 A
1$
#1410000
0$
#1415000
1/
b1 A
1$
#1420000
b10110100 -
b10110100 C
b10110100 F
b11110 2
b11110 9
0$
#1425000
0/
b10 A
1$
#1430000
0$
#1435000
1.
b100 A
1$
#1440000
0$
#1445000
0.
b101 A
1$
#1450000
0$
#1455000
1/
b1 A
1$
#1460000
b101101000 -
b101101000 C
b101101000 F
b11101 2
b11101 9
0$
#1465000
0/
b10 A
1$
#1470000
0$
#1475000
1.
b100 A
1$
#1480000
0$
#1485000
0.
b101 A
1$
#1490000
0$
#1495000
1/
b1 A
1$
#1500000
b1011010000 -
b1011010000 C
b1011010000 F
b11100 2
b11100 9
0$
#1505000
0/
b10 A
1$
#1510000
0$
#1515000
1.
b100 A
1$
#1520000
0$
#1525000
0.
b101 A
1$
#1530000
0$
#1535000
1/
b1 A
1$
#1540000
b10110100000 -
b10110100000 C
b10110100000 F
b11011 2
b11011 9
0$
#1545000
0/
b10 A
1$
#1550000
0$
#1555000
1.
b100 A
1$
#1560000
0$
#1565000
0.
b101 A
1$
#1570000
0$
#1575000
1/
b1 A
1$
#1580000
b101101000000 -
b101101000000 C
b101101000000 F
b11010 2
b11010 9
0$
#1585000
0/
b10 A
1$
#1590000
0$
#1595000
1.
b100 A
1$
#1600000
0$
#1605000
0.
b101 A
1$
#1610000
0$
#1615000
1/
b1 A
1$
#1620000
b1011010000000 -
b1011010000000 C
b1011010000000 F
b11001 2
b11001 9
0$
#1625000
0/
b10 A
1$
#1630000
0$
#1635000
1.
b100 A
1$
#1640000
0$
#1645000
0.
b101 A
1$
#1650000
0$
#1655000
1/
b1 A
1$
#1660000
b10110100000000 -
b10110100000000 C
b10110100000000 F
b11000 2
b11000 9
0$
#1665000
0/
b10 A
1$
#1670000
0$
#1675000
1.
b100 A
1$
#1680000
0$
#1685000
0.
b101 A
1$
#1690000
0$
#1695000
1/
b1 A
1$
#1700000
b101101000000000 -
b101101000000000 C
b101101000000000 F
b10111 2
b10111 9
0$
#1705000
0/
b10 A
1$
#1710000
0$
#1715000
1.
b100 A
1$
#1720000
0$
#1725000
0.
b101 A
1$
#1730000
0$
#1735000
1/
b1 A
1$
#1740000
b1011010000000000 -
b1011010000000000 C
b1011010000000000 F
b10110 2
b10110 9
0$
#1745000
0/
b10 A
1$
#1750000
0$
#1755000
1.
b100 A
1$
#1760000
0$
#1765000
0.
b101 A
1$
#1770000
0$
#1775000
1/
b1 A
1$
#1780000
b10110100000000000 -
b10110100000000000 C
b10110100000000000 F
b10101 2
b10101 9
0$
#1785000
0/
b10 A
1$
#1790000
0$
#1795000
1.
b100 A
1$
#1800000
0$
#1805000
0.
b101 A
1$
#1810000
0$
#1815000
1/
b1 A
1$
#1820000
b101101000000000000 -
b101101000000000000 C
b101101000000000000 F
b10100 2
b10100 9
0$
#1825000
0/
b10 A
1$
#1830000
0$
#1835000
1.
b100 A
1$
#1840000
0$
#1845000
0.
b101 A
1$
#1850000
0$
#1855000
1/
b1 A
1$
#1860000
b1011010000000000000 -
b1011010000000000000 C
b1011010000000000000 F
b10011 2
b10011 9
0$
#1865000
0/
b10 A
1$
#1870000
0$
#1875000
1.
b100 A
1$
#1880000
0$
#1885000
0.
b101 A
1$
#1890000
0$
#1895000
1/
b1 A
1$
#1900000
b10110100000000000000 -
b10110100000000000000 C
b10110100000000000000 F
b10010 2
b10010 9
0$
#1905000
0/
b10 A
1$
#1910000
0$
#1915000
1.
b100 A
1$
#1920000
0$
#1925000
0.
b101 A
1$
#1930000
0$
#1935000
1/
b1 A
1$
#1940000
b101101000000000000000 -
b101101000000000000000 C
b101101000000000000000 F
b10001 2
b10001 9
0$
#1945000
0/
b10 A
1$
#1950000
0$
#1955000
1.
b100 A
1$
#1960000
0$
#1965000
0.
b101 A
1$
#1970000
0$
#1975000
1/
b1 A
1$
#1980000
b1011010000000000000000 -
b1011010000000000000000 C
b1011010000000000000000 F
b10000 2
b10000 9
0$
#1985000
0/
b10 A
1$
#1990000
0$
#1995000
1.
b100 A
1$
#2000000
0$
#2005000
0.
b101 A
1$
#2010000
0$
#2015000
1/
b1 A
1$
#2020000
b10110100000000000000000 -
b10110100000000000000000 C
b10110100000000000000000 F
b1111 2
b1111 9
0$
#2025000
0/
b10 A
1$
#2030000
0$
#2035000
1.
b100 A
1$
#2040000
0$
#2045000
0.
b101 A
1$
#2050000
0$
#2055000
1/
b1 A
1$
#2060000
b101101000000000000000000 -
b101101000000000000000000 C
b101101000000000000000000 F
b1110 2
b1110 9
0$
#2065000
0/
b10 A
1$
#2070000
0$
#2075000
1.
b100 A
1$
#2080000
0$
#2085000
0.
b101 A
1$
#2090000
0$
#2095000
1/
b1 A
1$
#2100000
b1011010000000000000000000 -
b1011010000000000000000000 C
b1011010000000000000000000 F
b1101 2
b1101 9
0$
#2105000
0/
b10 A
1$
#2110000
0$
#2115000
1.
b100 A
1$
#2120000
0$
#2125000
0.
b101 A
1$
#2130000
0$
#2135000
1/
b1 A
1$
#2140000
b10110100000000000000000000 -
b10110100000000000000000000 C
b10110100000000000000000000 F
b1100 2
b1100 9
0$
#2145000
0/
b10 A
1$
#2150000
0$
#2155000
1.
b100 A
1$
#2160000
0$
#2165000
0.
b101 A
1$
#2170000
0$
#2175000
1/
b1 A
1$
#2180000
b101101000000000000000000000 -
b101101000000000000000000000 C
b101101000000000000000000000 F
b1011 2
b1011 9
0$
#2185000
0/
b10 A
1$
#2190000
0$
#2195000
1.
b100 A
1$
#2200000
0$
#2205000
0.
b101 A
1$
#2210000
0$
#2215000
1/
b1 A
1$
#2220000
b1011010000000000000000000000 -
b1011010000000000000000000000 C
b1011010000000000000000000000 F
b1010 2
b1010 9
0$
#2225000
0/
b10 A
1$
#2230000
0$
#2235000
1.
b100 A
1$
#2240000
0$
#2245000
0.
b101 A
1$
#2250000
0$
#2255000
1/
b1 A
1$
#2260000
b10110100000000000000000000000 -
b10110100000000000000000000000 C
b10110100000000000000000000000 F
b1001 2
b1001 9
0$
#2265000
0/
b10 A
1$
#2270000
0$
#2275000
1.
b100 A
1$
#2280000
0$
#2285000
0.
b101 A
1$
#2290000
0$
#2295000
1/
b1 A
1$
#2300000
b101101000000000000000000000000 -
b101101000000000000000000000000 C
b101101000000000000000000000000 F
b1000 2
b1000 9
0$
#2305000
0/
b10 A
1$
#2310000
0$
#2315000
1.
b100 A
1$
#2320000
0$
#2325000
0.
b101 A
1$
#2330000
0$
#2335000
1/
b1 A
1$
#2340000
b1011010000000000000000000000000 -
b1011010000000000000000000000000 C
b1011010000000000000000000000000 F
b111 2
b111 9
0$
#2345000
0/
b10 A
1$
#2350000
0$
#2355000
1.
b100 A
1$
#2360000
0$
#2365000
0.
b101 A
1$
#2370000
0$
#2375000
1/
b1 A
1$
#2380000
b10110100000000000000000000000000 -
b10110100000000000000000000000000 C
b10110100000000000000000000000000 F
b110 2
b110 9
0$
#2385000
0/
b10 A
1$
#2390000
0$
#2395000
1.
b100 A
1$
#2400000
0$
#2405000
0.
b101 A
1$
#2410000
0$
#2415000
1/
b1 A
1$
#2420000
b11111111111111111111111111111011 4
b11111111111111111111111111111011 E
b11111111111111111111111111111011 L
b1 !
b1 +
b1 1
b1 D
b1 K
b1101000000000000000000000000000 -
b1101000000000000000000000000000 C
b101101000000000000000000000000000 F
b101 2
b101 9
0$
#2425000
0/
b10 A
1$
#2430000
0$
#2435000
1.
b100 A
1$
#2440000
0$
#2445000
0.
b101 A
1$
#2450000
0$
#2455000
1/
b1 A
1$
#2460000
b11111111111111111111111111111100 4
b11111111111111111111111111111100 E
b11111111111111111111111111111100 L
b10 !
b10 +
b10 1
b10 D
b10 K
b11010000000000000000000000000000 -
b11010000000000000000000000000000 C
b1011010000000000000000000000000000 F
b100 2
b100 9
0$
#2465000
0/
b10 A
1$
#2470000
0$
#2475000
1.
b100 A
1$
#2480000
0$
#2485000
0.
b101 A
1$
#2490000
0$
#2495000
1/
b1 A
1$
#2500000
b11111111111111111111111111111111 4
b11111111111111111111111111111111 E
b11111111111111111111111111111111 L
b101 !
b101 +
b101 1
b101 D
b101 K
b10100000000000000000000000000000 -
b10100000000000000000000000000000 C
b10110100000000000000000000000000000 F
b11 2
b11 9
0$
#2505000
0/
b10 A
1$
#2510000
0$
#2515000
1.
b100 A
1$
#2520000
0$
#2525000
0.
b101 A
1$
#2530000
0$
#2535000
1/
b1 A
1$
