Tarea5/control_mult.v
module control_mult( clk, rst, lsb_B, init, z, done, sh, reset, add );
  input clk, rst, lsb_B, init, z;
  output reg done, sh, reset, add;

  parameter START = 3'b000;
  parameter CHECK = 3'b001;
  parameter SHIFT = 3'b010;
  parameter ADD = 3'b011;
  parameter END = 3'b100;
  reg [2:0] state;

  initial begin
    done = 0;
    sh = 0;
    reset = 0;
    add = 0;
    state = 0;
  end

  reg [3:0] count;

always @(posedge clk) begin
  if (rst) begin
    state = START;
  end else begin
  case(state)

  START:begin
    count=0;
    if(init)
      state = CHECK;
    else
      state = START;
  end

  CHECK:
    if(lsb_B)
      state = ADD;
    else
      state = SHIFT;
  SHIFT:
    if(z)
      state = END;
    else
      state = CHECK;
  
  ADD:
    state = SHIFT;
  
  END:begin
    count = count + 1;
    state = (count>9) ? START : END ;
  end
  
  default: state = START;

  endcase
  end
end

always @(state) 
begin
  case(state)
    START:begin
      done = 0;
      sh = 0;
      reset = 1;
      add = 0;
    end

    CHECK:begin
      done = 0;
      sh = 0;
      reset = 0;
      add = 0;
    end

    SHIFT:begin
      done = 0;
      sh = 1;
      reset = 0;
      add = 0;
    end

    ADD:begin
      done = 0;
      sh = 0;
      reset = 0;
      add = 1;
    end

    END:begin
      done = 1;
      sh = 0;
      reset = 0;
      add = 0;
    end

    default:begin
      done = 0;
      sh = 0;
      reset = 0;
      add = 0;
    end
  endcase
end
endmodule

Tarea5/mult_32.v
// --- CAJA PRINCIPAL DEL CAMINO DE DATOS ---
module mult_32(clk, rst, init, A, B, pp, done);
    input rst;
    input clk;
    input init;
    input [15:0] A;
    input [15:0] B;
    output [31:0] pp;        // Resultado final
    output done;

    wire w_sh;
    wire w_reset;
    wire w_add;
    wire w_z;

    wire [31:0] w_A;
    wire [15:0] w_B;

    // Conectamos las piezas internas
    rsr  rsr0  (.clk(clk), .in_B(B), .shift(w_sh), .load(w_reset), .s_B(w_B));
    lsr  lsr0  (.clk(clk), .in_A(A), .shift(w_sh), .load(w_reset), .s_A(w_A));
    comp comp0 (.B(w_B), .z(z));
    acc  acc0  (.clk(clk), .A(w_A), .add(w_add), .rst(w_reset), .pp(pp));
    control_mult control0 (.clk(clk),.rst(rst),.lsb_B(w_B[0]),.init(init),.z(w_z),.done(done),.sh(w_sh),.reset(w_reset),.add(w_add));
endmodule

// --- PIEZAS INTERNAS (Del libro del profe) ---
module rsr(clk, in_B, shift, load, s_B);
  input clk;
  input [15:0]in_B;
  input load;
  input shift;
  output reg [15:0]s_B;
  always @(negedge clk)
    if (load)
     s_B <= in_B;
     else
     begin
     if(shift) s_B <= s_B >> 1; 
     else s_B <= s_B;
     end
endmodule

module lsr(clk, in_A, shift, load, s_A);
  input clk;
  input shift;
  input load;
  input [15:0] in_A;
  output reg [31:0] s_A;
  always @(negedge clk)
  if (load)
    s_A = in_A;
   else
    begin
    if(shift) s_A=s_A<<1;
    else s_A=s_A;
  end
endmodule

module comp(B, z);
  input [15:0] B; 
  output z;
  reg tmp;

  initial tmp=0;
  assign z = (tmp);

    always@(*)
      tmp=(B==0)? 1'b1:1'b0;
endmodule
module acc(clk, A, add, rst, pp);
  input clk;
  input [31:0] A;
  input add;
  input rst;
  output reg [31:0] pp;

  initial pp = 0;
  
  
  always @(negedge clk) 
    if (rst)
      pp <= 32'h00000000; 
    else
      begin
        if (add) pp <= pp + A; 
        else pp <= pp;
      end
endmodule

Tarea5/mult_32_TB.v
`timescale 1ns / 1ps
`define SIMULATION
module mult_32_TB;
  reg clk;
  reg rst;
  reg reset;
  reg start;
  reg [15:0]in_A;
  reg [15:0]in_B;
  wire [31:0] pp;
  wire done;
  mult_32 uut (.clk(clk), .rst(rst), .init(start), .A(in_A), .B(in_B), .pp(pp), .done(done));
  parameter PERIOD = 20;
  parameter real DUTY_CYCLE = 0.5;
  parameter OFFSET = 0;
  reg [20:0] i;
    event reset_trigger;
    event reset_done_trigger;
    initial begin
      forever begin
      @ (reset_trigger);
        @ (negedge clk);
        rst = 1;
        @ (negedge clk);
        rst = 0;
        -> reset_done_trigger;
      end
    end
  initial begin 
    clk = 0; reset = 1; start = 0; in_A = 16'b1000; in_B = 16'b10;
  end

  initial begin // Process for clk
    #OFFSET;
    forever
    begin
      clk = 1'b0;
      #(PERIOD-(PERIOD*DUTY_CYCLE)) clk = 1'b1;
      #(PERIOD*DUTY_CYCLE);
    end
  end

  initial begin 
    #10 -> reset_trigger;
    @ (reset_done_trigger);
    @ (posedge clk);
    start = 0;
    @ (posedge clk);
    start = 1;
    for(i=0; i<2; i=i+1) begin
      @ (posedge clk);
    end
      start = 0;
    for(i=0; i<17; i=i+1) begin
      @ (posedge clk);
    end
  end
  initial begin: TEST_CASE
    $dumpfile("mult_32_TB.vcd");
    $dumpvars(-1, uut);
    #((PERIOD*DUTY_CYCLE)*120) $finish;
  end

endmodule

Tarea5/mult_32_TB.vcd
$date
	Thu Apr 16 16:32:31 2026
$end
$version
	Icarus Verilog
$end
$timescale
	1ps
$end
$scope module mult_32_TB $end
$scope module uut $end
$var wire 16 ! A [15:0] $end
$var wire 16 " B [15:0] $end
$var wire 1 # clk $end
$var wire 1 $ init $end
$var wire 1 % rst $end
$var wire 1 & w_z $end
$var wire 1 ' z $end
$var wire 1 ( w_sh $end
$var wire 1 ) w_reset $end
$var wire 1 * w_add $end
$var wire 16 + w_B [15:0] $end
$var wire 32 , w_A [31:0] $end
$var wire 32 - pp [31:0] $end
$var wire 1 . done $end
$scope module acc0 $end
$var wire 1 # clk $end
$var wire 1 ) rst $end
$var wire 1 * add $end
$var wire 32 / A [31:0] $end
$var reg 32 0 pp [31:0] $end
$upscope $end
$scope module comp0 $end
$var wire 1 ' z $end
$var wire 16 1 B [15:0] $end
$var reg 1 2 tmp $end
$upscope $end
$scope module control0 $end
$var wire 1 # clk $end
$var wire 1 $ init $end
$var wire 1 3 lsb_B $end
$var wire 1 % rst $end
$var wire 1 & z $end
$var parameter 3 4 ADD $end
$var parameter 3 5 CHECK $end
$var parameter 3 6 END $end
$var parameter 3 7 SHIFT $end
$var parameter 3 8 START $end
$var reg 1 * add $end
$var reg 4 9 count [3:0] $end
$var reg 1 . done $end
$var reg 1 ) reset $end
$var reg 1 ( sh $end
$var reg 3 : state [2:0] $end
$upscope $end
$scope module lsr0 $end
$var wire 1 # clk $end
$var wire 16 ; in_A [15:0] $end
$var wire 1 ) load $end
$var wire 1 ( shift $end
$var reg 32 < s_A [31:0] $end
$upscope $end
$scope module rsr0 $end
$var wire 1 # clk $end
$var wire 16 = in_B [15:0] $end
$var wire 1 ) load $end
$var wire 1 ( shift $end
$var reg 16 > s_B [15:0] $end
$upscope $end
$upscope $end
$upscope $end
$enddefinitions $end
$comment Show the parameter values. $end
$dumpall
b0 8
b10 7
b100 6
b1 5
b11 4
$end
#0
$dumpvars
b10 >
b10 =
b1000 <
b1000 ;
b0 :
bx 9
03
02
b10 1
b0 0
b1000 /
0.
b0 -
b1000 ,
b10 +
0*
1)
0(
0'
z&
x%
0$
0#
b10 "
b1000 !
$end
#10000
b0 9
1#
#20000
1%
0#
#30000
1#
#40000
0%
0#
#50000
1#
#60000
0#
#70000
1$
1#
#80000
0#
#90000
0)
b1 :
1#
#100000
0#
#110000
1(
0$
b10 :
1#
#120000
13
b1 +
b1 1
b1 >
b10000 ,
b10000 /
b10000 <
0#
#130000
0(
b1 :
1#
#140000
0#
#150000
1*
b11 :
1#
#160000
b10000 -
b10000 0
0#
#170000
0*
1(
b10 :
1#
#180000
03
1'
12
b0 +
b0 1
b0 >
b100000 ,
b100000 /
b100000 <
0#
#190000
0(
b1 :
1#
#200000
0#
#210000
1(
b10 :
1#
#220000
b1000000 ,
b1000000 /
b1000000 <
0#
#230000
0(
b1 :
1#
#240000
0#
#250000
1(
b10 :
1#
#260000
b10000000 ,
b10000000 /
b10000000 <
0#
#270000
0(
b1 :
1#
#280000
0#
#290000
1(
b10 :
1#
#300000
b100000000 ,
b100000000 /
b100000000 <
0#
#310000
0(
b1 :
1#
#320000
0#
#330000
1(
b10 :
1#
#340000
b1000000000 ,
b1000000000 /
b1000000000 <
0#
#350000
0(
b1 :
1#
#360000
0#
#370000
1(
b10 :
1#
#380000
b10000000000 ,
b10000000000 /
b10000000000 <
0#
#390000
0(
b1 :
1#
#400000
0#
#410000
1(
b10 :
1#
#420000
b100000000000 ,
b100000000000 /
b100000000000 <
0#
#430000
0(
b1 :
1#
#440000
0#
#450000
1(
b10 :
1#
#460000
b1000000000000 ,
b1000000000000 /
b1000000000000 <
0#
#470000
0(
b1 :
1#
#480000
0#
#490000
1(
b10 :
1#
#500000
b10000000000000 ,
b10000000000000 /
b10000000000000 <
0#
#510000
0(
b1 :
1#
#520000
0#
#530000
1(
b10 :
1#
#540000
b100000000000000 ,
b100000000000000 /
b100000000000000 <
0#
#550000
0(
b1 :
1#
#560000
0#
#570000
1(
b10 :
1#
#580000
b1000000000000000 ,
b1000000000000000 /
b1000000000000000 <
0#
#590000
0(
b1 :
1#
#600000
0#
#610000
1(
b10 :
1#
#620000
b10000000000000000 ,
b10000000000000000 /
b10000000000000000 <
0#
#630000
0(
b1 :
1#
#640000
0#
#650000
1(
b10 :
1#
#660000
b100000000000000000 ,
b100000000000000000 /
b100000000000000000 <
0#
#670000
0(
b1 :
1#
#680000
0#
#690000
1(
b10 :
1#
#700000
b1000000000000000000 ,
b1000000000000000000 /
b1000000000000000000 <
0#
#710000
0(
b1 :
1#
#720000
0#
#730000
1(
b10 :
1#
#740000
b10000000000000000000 ,
b10000000000000000000 /
b10000000000000000000 <
0#
#750000
0(
b1 :
1#
#760000
0#
#770000
1(
b10 :
1#
#780000
b100000000000000000000 ,
b100000000000000000000 /
b100000000000000000000 <
0#
#790000
0(
b1 :
1#
#800000
0#
#810000
1(
b10 :
1#
#820000
b1000000000000000000000 ,
b1000000000000000000000 /
b1000000000000000000000 <
0#
#830000
0(
b1 :
1#
#840000
0#
#850000
1(
b10 :
1#
#860000
b10000000000000000000000 ,
b10000000000000000000000 /
b10000000000000000000000 <
0#
#870000
0(
b1 :
1#
#880000
0#
#890000
1(
b10 :
1#
#900000
b100000000000000000000000 ,
b100000000000000000000000 /
b100000000000000000000000 <
0#
#910000
0(
b1 :
1#
#920000
0#
#930000
1(
b10 :
1#
#940000
b1000000000000000000000000 ,
b1000000000000000000000000 /
b1000000000000000000000000 <
0#
#950000
0(
b1 :
1#
#960000
0#
#970000
1(
b10 :
1#
#980000
b10000000000000000000000000 ,
b10000000000000000000000000 /
b10000000000000000000000000 <
0#
#990000
0(
b1 :
1#
#1000000
0#
#1010000
1(
b10 :
1#
#1020000
b100000000000000000000000000 ,
b100000000000000000000000000 /
b100000000000000000000000000 <
0#
#1030000
0(
b1 :
1#
#1040000
0#
#1050000
1(
b10 :
1#
#1060000
b1000000000000000000000000000 ,
b1000000000000000000000000000 /
b1000000000000000000000000000 <
0#
#1070000
0(
b1 :
1#
#1080000
0#
#1090000
1(
b10 :
1#
#1100000
b10000000000000000000000000000 ,
b10000000000000000000000000000 /
b10000000000000000000000000000 <
0#
#1110000
0(
b1 :
1#
#1120000
0#
#1130000
1(
b10 :
1#
#1140000
b100000000000000000000000000000 ,
b100000000000000000000000000000 /
b100000000000000000000000000000 <
0#
#1150000
0(
b1 :
1#
#1160000
0#
#1170000
1(
b10 :
1#
#1180000
b1000000000000000000000000000000 ,
b1000000000000000000000000000000 /
b1000000000000000000000000000000 <
0#
#1190000
0(
b1 :
1#
